rtl/ddr4_phy_iface.v
// DDR4 PHY Interface — Abstract PHY Layer
// Bridges the controller's command/data buses to the DDR4 SDRAM pad ring.
// In a real ASIC/FPGA implementation this module would be replaced with
// vendor-specific I/O primitives (Xilinx IOSERDES, Intel LVDS_DDR, etc.).
// Here it provides a behavioural model that satisfies the pad naming required
// by the top-level integration.
module ddr4_phy_iface #(
    parameter NUM_RANKS = 1,
    parameter DQ_WIDTH  = 72,   // 64 data + 8 ECC
    parameter DQS_WIDTH = 9     // one DQS per byte lane
)(
    input  wire                  clk,
    input  wire                  rst_n,

    // Controller command bus (from timing engine / scheduler)
    input  wire                  ctrl_cmd_valid,
    input  wire                  ctrl_act_n,
    input  wire                  ctrl_ras_n,
    input  wire                  ctrl_cas_n,
    input  wire                  ctrl_we_n,
    input  wire [1:0]            ctrl_bg,
    input  wire [1:0]            ctrl_ba,
    input  wire [16:0]           ctrl_a,
    input  wire [NUM_RANKS-1:0]  ctrl_cs_n,
    input  wire [NUM_RANKS-1:0]  ctrl_cke,
    input  wire [NUM_RANKS-1:0]  ctrl_odt,
    input  wire                  ctrl_reset_n,

    // Data bus from controller
    input  wire [DQ_WIDTH-1:0]   ctrl_dq_out,
    input  wire [DQS_WIDTH-1:0]  ctrl_dq_oe,   // per-byte-lane output enable
    input  wire [DQS_WIDTH-1:0]  ctrl_dqs_oe,  // DQS output enable

    // Captured data returned to controller
    output reg  [DQ_WIDTH-1:0]   phy_dq_in,
    output reg                   phy_dqs_valid,

    // DDR4 SDRAM pad interface
    // CK is driven combinatorially to track clk at full data rate
    output wire [NUM_RANKS-1:0]  ddr4_ck_t,
    output wire [NUM_RANKS-1:0]  ddr4_ck_c,
    output reg  [NUM_RANKS-1:0]  ddr4_cke,
    output reg  [NUM_RANKS-1:0]  ddr4_cs_n,
    output reg                   ddr4_act_n,
    output reg                   ddr4_ras_n,
    output reg                   ddr4_cas_n,
    output reg                   ddr4_we_n,
    output reg  [1:0]            ddr4_bg,
    output reg  [1:0]            ddr4_ba,
    output reg  [16:0]           ddr4_a,
    output reg  [NUM_RANKS-1:0]  ddr4_odt,
    output reg                   ddr4_reset_n,
    // DQ / DQS are modelled as separate output / input registers
    // (tri-state semantics are represented by the oe signals)
    output reg  [DQ_WIDTH-1:0]   ddr4_dq_out,
    input  wire [DQ_WIDTH-1:0]   ddr4_dq_in,
    output reg  [DQS_WIDTH-1:0]  ddr4_dqs_t,
    output reg  [DQS_WIDTH-1:0]  ddr4_dqs_c,
    output reg  [DQS_WIDTH-1:0]  ddr4_dm_dbi_n
);

    // ---------------------------------------------------------------
    // CK generation — continuous (combinatorial) differential clock
    // ddr4_ck_t tracks clk; ddr4_ck_c is its complement.
    // This is the correct model: a real PHY forwards clk to the DRAM.
    // ---------------------------------------------------------------
    assign ddr4_ck_t = rst_n ? {NUM_RANKS{clk}} : {NUM_RANKS{1'b0}};
    assign ddr4_ck_c = rst_n ? {NUM_RANKS{~clk}} : {NUM_RANKS{1'b1}};

    // ---------------------------------------------------------------
    // Command / address register slice (one-cycle pipeline stage)
    // ---------------------------------------------------------------
    always @(posedge clk) begin
        if (!rst_n) begin
            ddr4_cke     <= {NUM_RANKS{1'b0}};
            ddr4_cs_n    <= {NUM_RANKS{1'b1}};
            ddr4_act_n   <= 1'b1;
            ddr4_ras_n   <= 1'b1;
            ddr4_cas_n   <= 1'b1;
            ddr4_we_n    <= 1'b1;
            ddr4_bg      <= 2'b00;
            ddr4_ba      <= 2'b00;
            ddr4_a       <= 17'h00000;
            ddr4_odt     <= {NUM_RANKS{1'b0}};
            ddr4_reset_n <= 1'b0;
        end else begin
            ddr4_cke     <= ctrl_cke;
            ddr4_reset_n <= ctrl_reset_n;
            ddr4_odt     <= ctrl_odt;

            if (ctrl_cmd_valid) begin
                ddr4_cs_n  <= ctrl_cs_n;
                ddr4_act_n <= ctrl_act_n;
                ddr4_ras_n <= ctrl_ras_n;
                ddr4_cas_n <= ctrl_cas_n;
                ddr4_we_n  <= ctrl_we_n;
                ddr4_bg    <= ctrl_bg;
                ddr4_ba    <= ctrl_ba;
                ddr4_a     <= ctrl_a;
            end else begin
                // NOP: deselect all ranks
                ddr4_cs_n  <= {NUM_RANKS{1'b1}};
                ddr4_act_n <= 1'b1;
                ddr4_ras_n <= 1'b1;
                ddr4_cas_n <= 1'b1;
                ddr4_we_n  <= 1'b1;
                ddr4_bg    <= 2'b00;
                ddr4_ba    <= 2'b00;
                ddr4_a     <= 17'h00000;
            end
        end
    end

    // ---------------------------------------------------------------
    // DQ / DQS output path
    // ---------------------------------------------------------------
    always @(posedge clk) begin
        if (!rst_n) begin
            ddr4_dq_out   <= {DQ_WIDTH{1'b0}};
            ddr4_dqs_t    <= {DQS_WIDTH{1'b0}};
            ddr4_dqs_c    <= {DQS_WIDTH{1'b1}};
            ddr4_dm_dbi_n <= {DQS_WIDTH{1'b1}};
        end else begin
            // Drive DQ only when OE is asserted per byte lane
            begin : dq_out_gen
                integer b;
                for (b = 0; b < DQS_WIDTH; b = b + 1) begin
                    if (ctrl_dq_oe[b])
                        ddr4_dq_out[b*8 +: 8] <= ctrl_dq_out[b*8 +: 8];
                    else
                        ddr4_dq_out[b*8 +: 8] <= 8'hzz; // tri-state model
                end
            end
            // DQS differential strobe
            begin : dqs_gen
                integer b;
                for (b = 0; b < DQS_WIDTH; b = b + 1) begin
                    if (ctrl_dqs_oe[b]) begin
                        ddr4_dqs_t[b] <= clk;
                        ddr4_dqs_c[b] <= ~clk;
                    end else begin
                        ddr4_dqs_t[b] <= 1'bz;
                        ddr4_dqs_c[b] <= 1'bz;
                    end
                end
            end
            ddr4_dm_dbi_n <= {DQS_WIDTH{1'b1}}; // DBI disabled
        end
    end

    // ---------------------------------------------------------------
    // DQ input path — capture on posedge with DQS-valid gating
    // ---------------------------------------------------------------
    // In this abstract model, ddr4_dq_in is captured directly and
    // phy_dqs_valid is asserted each cycle that DQS OE is de-asserted
    // (indicating read data has arrived from DRAM).
    wire dqs_oe_any = |ctrl_dqs_oe;
    reg dqs_oe_prev;
    always @(posedge clk) begin
        if (!rst_n) begin
            phy_dq_in     <= {DQ_WIDTH{1'b0}};
            phy_dqs_valid <= 1'b0;
            dqs_oe_prev   <= 1'b0;
        end else begin
            dqs_oe_prev   <= dqs_oe_any;
            phy_dqs_valid <= 1'b0;
            // Capture read data when not in write-OE mode
            if (!dqs_oe_any) begin
                phy_dq_in     <= ddr4_dq_in;
                phy_dqs_valid <= 1'b1;
            end
        end
    end

endmodule

tb/ddr4_phy_iface_tb.v
`timescale 1ns/1ps
// Testbench for ddr4_phy_iface
// Tests: DDR4 pad output timing, DQ tristate during read, DQS preamble,
//        CK differential generation, command bus pass-through.
module ddr4_phy_iface_tb;

    localparam NUM_RANKS = 1;
    localparam DQ_WIDTH  = 72;
    localparam DQS_WIDTH = 9;

    reg  clk, rst_n;

    // Controller command bus inputs
    reg                  ctrl_cmd_valid;
    reg                  ctrl_act_n, ctrl_ras_n, ctrl_cas_n, ctrl_we_n;
    reg  [1:0]           ctrl_bg, ctrl_ba;
    reg  [16:0]          ctrl_a;
    reg  [NUM_RANKS-1:0] ctrl_cs_n;
    reg  [NUM_RANKS-1:0] ctrl_cke;
    reg  [NUM_RANKS-1:0] ctrl_odt;
    reg                  ctrl_reset_n;

    // Data bus
    reg  [DQ_WIDTH-1:0]  ctrl_dq_out;
    reg  [DQS_WIDTH-1:0] ctrl_dq_oe;
    reg  [DQS_WIDTH-1:0] ctrl_dqs_oe;

    // DQ input (from DRAM)
    reg  [DQ_WIDTH-1:0]  ddr4_dq_in;

    // Outputs
    wire [DQ_WIDTH-1:0]  phy_dq_in;
    wire                 phy_dqs_valid;

    wire [NUM_RANKS-1:0] ddr4_ck_t, ddr4_ck_c;
    wire [NUM_RANKS-1:0] ddr4_cke, ddr4_cs_n;
    wire                 ddr4_act_n, ddr4_ras_n, ddr4_cas_n, ddr4_we_n;
    wire [1:0]           ddr4_bg, ddr4_ba;
    wire [16:0]          ddr4_a;
    wire [NUM_RANKS-1:0] ddr4_odt;
    wire                 ddr4_reset_n;
    wire [DQ_WIDTH-1:0]  ddr4_dq_out;
    wire [DQS_WIDTH-1:0] ddr4_dqs_t, ddr4_dqs_c;
    wire [DQS_WIDTH-1:0] ddr4_dm_dbi_n;

    ddr4_phy_iface #(
        .NUM_RANKS(NUM_RANKS),
        .DQ_WIDTH(DQ_WIDTH),
        .DQS_WIDTH(DQS_WIDTH)
    ) dut (
        .clk            (clk),
        .rst_n          (rst_n),
        .ctrl_cmd_valid (ctrl_cmd_valid),
        .ctrl_act_n     (ctrl_act_n),
        .ctrl_ras_n     (ctrl_ras_n),
        .ctrl_cas_n     (ctrl_cas_n),
        .ctrl_we_n      (ctrl_we_n),
        .ctrl_bg        (ctrl_bg),
        .ctrl_ba        (ctrl_ba),
        .ctrl_a         (ctrl_a),
        .ctrl_cs_n      (ctrl_cs_n),
        .ctrl_cke       (ctrl_cke),
        .ctrl_odt       (ctrl_odt),
        .ctrl_reset_n   (ctrl_reset_n),
        .ctrl_dq_out    (ctrl_dq_out),
        .ctrl_dq_oe     (ctrl_dq_oe),
        .ctrl_dqs_oe    (ctrl_dqs_oe),
        .phy_dq_in      (phy_dq_in),
        .phy_dqs_valid  (phy_dqs_valid),
        .ddr4_ck_t      (ddr4_ck_t),
        .ddr4_ck_c      (ddr4_ck_c),
        .ddr4_cke       (ddr4_cke),
        .ddr4_cs_n      (ddr4_cs_n),
        .ddr4_act_n     (ddr4_act_n),
        .ddr4_ras_n     (ddr4_ras_n),
        .ddr4_cas_n     (ddr4_cas_n),
        .ddr4_we_n      (ddr4_we_n),
        .ddr4_bg        (ddr4_bg),
        .ddr4_ba        (ddr4_ba),
        .ddr4_a         (ddr4_a),
        .ddr4_odt       (ddr4_odt),
        .ddr4_reset_n   (ddr4_reset_n),
        .ddr4_dq_out    (ddr4_dq_out),
        .ddr4_dq_in     (ddr4_dq_in),
        .ddr4_dqs_t     (ddr4_dqs_t),
        .ddr4_dqs_c     (ddr4_dqs_c),
        .ddr4_dm_dbi_n  (ddr4_dm_dbi_n)
    );

    initial clk = 0;
    always #5 clk = ~clk;

    initial begin
        $dumpfile("results/phase-integration/ddr4_phy_iface.vcd");
        $dumpvars(0, ddr4_phy_iface_tb);
    end

    integer pass_cnt = 0;
    integer fail_cnt = 0;

    task wait_clk;
        input integer n;
        integer i;
        begin for (i=0; i<n; i=i+1) @(posedge clk); end
    endtask

    initial begin
        // Initialise inputs
        rst_n          = 0;
        ctrl_cmd_valid = 0;
        ctrl_act_n     = 1; ctrl_ras_n = 1; ctrl_cas_n = 1; ctrl_we_n = 1;
        ctrl_bg        = 0; ctrl_ba = 0; ctrl_a = 0;
        ctrl_cs_n      = {NUM_RANKS{1'b1}};
        ctrl_cke       = {NUM_RANKS{1'b0}};
        ctrl_odt       = {NUM_RANKS{1'b0}};
        ctrl_reset_n   = 0;
        ctrl_dq_out    = 0;
        ctrl_dq_oe     = 0;
        ctrl_dqs_oe    = 0;
        ddr4_dq_in     = 0;

        repeat(5) @(posedge clk);
        @(negedge clk); rst_n = 1;
        wait_clk(3);

        // -------------------------------------------------------
        // Test 1: CK differential clock generation
        // -------------------------------------------------------
        $display("Test 1: CK differential output");
        wait_clk(2);
        @(posedge clk); #1;
        if (ddr4_ck_t === ddr4_ck_c)
            $fatal(1, "T1 FAIL: ck_t and ck_c must be complementary");
        $display("  T1: ddr4_ck_t=%b ddr4_ck_c=%b (differential)", ddr4_ck_t, ddr4_ck_c);
        pass_cnt = pass_cnt + 1;
        wait_clk(2);

        // -------------------------------------------------------
        // Test 2: Command bus — ACTIVATE command reaches pads
        // -------------------------------------------------------
        $display("Test 2: ACT command propagated to DDR4 pads");
        @(negedge clk);
        ctrl_cmd_valid = 1'b1;
        ctrl_act_n     = 1'b0;  // ACT
        ctrl_ras_n     = 1'b1;
        ctrl_cas_n     = 1'b1;
        ctrl_we_n      = 1'b1;
        ctrl_cs_n      = {NUM_RANKS{1'b0}};  // select rank 0
        ctrl_cke       = {NUM_RANKS{1'b1}};
        ctrl_bg        = 2'b01;
        ctrl_ba        = 2'b10;
        ctrl_a         = 17'h1ABCD;
        @(posedge clk); @(posedge clk); #1;
        if (ddr4_act_n !== 1'b0)
            $fatal(1, "T2 FAIL: ddr4_act_n should be 0 for ACT command");
        if (ddr4_a !== 17'h1ABCD)
            $fatal(1, "T2 FAIL: ddr4_a mismatch: %h vs %h", ddr4_a, 17'h1ABCD);
        if (ddr4_cs_n !== {NUM_RANKS{1'b0}})
            $fatal(1, "T2 FAIL: ddr4_cs_n should be 0");
        $display("  T2: ACT command on pads OK (act_n=%b, a=%h)", ddr4_act_n, ddr4_a);
        pass_cnt = pass_cnt + 1;
        @(negedge clk); ctrl_cmd_valid = 1'b0;
        ctrl_act_n = 1'b1;
        wait_clk(2);

        // -------------------------------------------------------
        // Test 3: DQ output when dq_oe is asserted
        // -------------------------------------------------------
        $display("Test 3: DQ output-enable and data drive");
        @(negedge clk);
        ctrl_dq_out = 72'hA5A5_A5A5_A5A5_A5A5_AA; // test pattern
        ctrl_dq_oe  = {DQS_WIDTH{1'b1}};  // all byte lanes OE
        ctrl_dqs_oe = {DQS_WIDTH{1'b1}};
        @(posedge clk); @(posedge clk); #1;
        // ddr4_dq_out[7:0] should match ctrl_dq_out[7:0] (byte lane 0)
        if (ddr4_dq_out[7:0] !== ctrl_dq_out[7:0])
            $fatal(1, "T3 FAIL: dq_out[7:0]=%h expected %h", ddr4_dq_out[7:0], ctrl_dq_out[7:0]);
        // DQS should toggle
        $display("  T3: DQ output path OK (dq_out[7:0]=%h)", ddr4_dq_out[7:0]);
        pass_cnt = pass_cnt + 1;
        wait_clk(2);

        // -------------------------------------------------------
        // Test 4: DQ tristate during read (dq_oe=0) — phy_dqs_valid
        // -------------------------------------------------------
        $display("Test 4: DQ tristate during read and phy_dqs_valid");
        @(negedge clk);
        ctrl_dq_oe  = {DQS_WIDTH{1'b0}};
        ctrl_dqs_oe = {DQS_WIDTH{1'b0}};
        ddr4_dq_in  = 72'h123456789ABCDEF012;
        @(posedge clk); @(posedge clk); #1;
        if (!phy_dqs_valid)
            $fatal(1, "T4 FAIL: phy_dqs_valid should be 1 when dqs_oe=0");
        if (phy_dq_in !== 72'h123456789ABCDEF012)
            $fatal(1, "T4 FAIL: phy_dq_in mismatch: got %h", phy_dq_in);
        $display("  T4: phy_dqs_valid=%b, phy_dq_in=%h", phy_dqs_valid, phy_dq_in);
        pass_cnt = pass_cnt + 1;
        wait_clk(2);

        // -------------------------------------------------------
        // Test 5: NOP / deselect — CS_N=1 propagated
        // -------------------------------------------------------
        $display("Test 5: NOP / deselect — ddr4_cs_n=1 after cmd_valid=0");
        @(negedge clk);
        ctrl_cmd_valid = 1'b0;
        ctrl_cs_n      = {NUM_RANKS{1'b1}};
        @(posedge clk); @(posedge clk); #1;
        if (ddr4_cs_n !== {NUM_RANKS{1'b1}})
            $fatal(1, "T5 FAIL: ddr4_cs_n should be all-1 on NOP");
        $display("  T5: NOP/deselect OK (ddr4_cs_n=%b)", ddr4_cs_n);
        pass_cnt = pass_cnt + 1;
        wait_clk(3);

        // -------------------------------------------------------
        // Test 6: RESET_N propagated
        // -------------------------------------------------------
        $display("Test 6: RESET_N propagation");
        @(negedge clk); ctrl_reset_n = 1'b1;
        @(posedge clk); @(posedge clk); #1;
        if (ddr4_reset_n !== 1'b1)
            $fatal(1, "T6 FAIL: ddr4_reset_n should be 1");
        $display("  T6: ddr4_reset_n=%b OK", ddr4_reset_n);
        pass_cnt = pass_cnt + 1;
        wait_clk(3);

        $display("=== RESULTS: %0d passed, %0d failed ===", pass_cnt, fail_cnt);
        if (fail_cnt == 0)
            $display("PASS: ddr4_phy_iface all tests passed");
        else
            $fatal(1, "FAIL: ddr4_phy_iface had %0d failures", fail_cnt);
        $finish;
    end

endmodule

results/phase-integration/ddr4_phy_iface.vcd
$date
	Thu Mar 12 11:02:57 2026
$end
$version
	Icarus Verilog
$end
$timescale
	1ps
$end
$scope module ddr4_phy_iface_tb $end
$var wire 1 ! phy_dqs_valid $end
$var wire 72 " phy_dq_in [71:0] $end
$var wire 1 # ddr4_we_n $end
$var wire 1 $ ddr4_reset_n $end
$var wire 1 % ddr4_ras_n $end
$var wire 1 & ddr4_odt $end
$var wire 9 ' ddr4_dqs_t [8:0] $end
$var wire 9 ( ddr4_dqs_c [8:0] $end
$var wire 72 ) ddr4_dq_out [71:0] $end
$var wire 9 * ddr4_dm_dbi_n [8:0] $end
$var wire 1 + ddr4_cs_n $end
$var wire 1 , ddr4_cke $end
$var wire 1 - ddr4_ck_t $end
$var wire 1 . ddr4_ck_c $end
$var wire 1 / ddr4_cas_n $end
$var wire 2 0 ddr4_bg [1:0] $end
$var wire 2 1 ddr4_ba [1:0] $end
$var wire 1 2 ddr4_act_n $end
$var wire 17 3 ddr4_a [16:0] $end
$var parameter 32 4 DQS_WIDTH $end
$var parameter 32 5 DQ_WIDTH $end
$var parameter 32 6 NUM_RANKS $end
$var reg 1 7 clk $end
$var reg 17 8 ctrl_a [16:0] $end
$var reg 1 9 ctrl_act_n $end
$var reg 2 : ctrl_ba [1:0] $end
$var reg 2 ; ctrl_bg [1:0] $end
$var reg 1 < ctrl_cas_n $end
$var reg 1 = ctrl_cke $end
$var reg 1 > ctrl_cmd_valid $end
$var reg 1 ? ctrl_cs_n $end
$var reg 9 @ ctrl_dq_oe [8:0] $end
$var reg 72 A ctrl_dq_out [71:0] $end
$var reg 9 B ctrl_dqs_oe [8:0] $end
$var reg 1 C ctrl_odt $end
$var reg 1 D ctrl_ras_n $end
$var reg 1 E ctrl_reset_n $end
$var reg 1 F ctrl_we_n $end
$var reg 72 G ddr4_dq_in [71:0] $end
$var reg 1 H rst_n $end
$var integer 32 I fail_cnt [31:0] $end
$var integer 32 J pass_cnt [31:0] $end
$scope module dut $end
$var wire 1 7 clk $end
$var wire 17 K ctrl_a [16:0] $end
$var wire 1 9 ctrl_act_n $end
$var wire 2 L ctrl_ba [1:0] $end
$var wire 2 M ctrl_bg [1:0] $end
$var wire 1 < ctrl_cas_n $end
$var wire 1 = ctrl_cke $end
$var wire 1 > ctrl_cmd_valid $end
$var wire 1 ? ctrl_cs_n $end
$var wire 9 N ctrl_dq_oe [8:0] $end
$var wire 72 O ctrl_dq_out [71:0] $end
$var wire 9 P ctrl_dqs_oe [8:0] $end
$var wire 1 C ctrl_odt $end
$var wire 1 D ctrl_ras_n $end
$var wire 1 E ctrl_reset_n $end
$var wire 1 F ctrl_we_n $end
$var wire 72 Q ddr4_dq_in [71:0] $end
$var wire 1 H rst_n $end
$var wire 1 R dqs_oe_any $end
$var wire 1 - ddr4_ck_t $end
$var wire 1 . ddr4_ck_c $end
$var parameter 32 S DQS_WIDTH $end
$var parameter 32 T DQ_WIDTH $end
$var parameter 32 U NUM_RANKS $end
$var reg 17 V ddr4_a [16:0] $end
$var reg 1 2 ddr4_act_n $end
$var reg 2 W ddr4_ba [1:0] $end
$var reg 2 X ddr4_bg [1:0] $end
$var reg 1 / ddr4_cas_n $end
$var reg 1 , ddr4_cke $end
$var reg 1 + ddr4_cs_n $end
$var reg 9 Y ddr4_dm_dbi_n [8:0] $end
$var reg 72 Z ddr4_dq_out [71:0] $end
$var reg 9 [ ddr4_dqs_c [8:0] $end
$var reg 9 \ ddr4_dqs_t [8:0] $end
$var reg 1 & ddr4_odt $end
$var reg 1 % ddr4_ras_n $end
$var reg 1 $ ddr4_reset_n $end
$var reg 1 # ddr4_we_n $end
$var reg 1 ] dqs_oe_prev $end
$var reg 72 ^ phy_dq_in [71:0] $end
$var reg 1 ! phy_dqs_valid $end
$scope begin dq_out_gen $end
$var integer 32 _ b [31:0] $end
$upscope $end
$scope begin dqs_gen $end
$var integer 32 ` b [31:0] $end
$upscope $end
$upscope $end
$scope task wait_clk $end
$var integer 32 a i [31:0] $end
$var integer 32 b n [31:0] $end
$upscope $end
$upscope $end
$enddefinitions $end
$comment Show the parameter values. $end
$dumpall
b1 U
b1001000 T
b1001 S
b1 6
b1001000 5
b1001 4
$end
#0
$dumpvars
bx b
bx a
bx `
bx _
bx ^
x]
bx \
bx [
bx Z
bx Y
bx X
bx W
bx V
0R
b0 Q
b0 P
b0 O
b0 N
b0 M
b0 L
b0 K
b0 J
b0 I
0H
b0 G
1F
0E
1D
0C
b0 B
b0 A
b0 @
1?
0>
0=
1<
b0 ;
b0 :
19
b0 8
07
bx 3
x2
bx 1
bx 0
x/
1.
0-
x,
x+
bx *
bx )
bx (
bx '
x&
x%
x$
x#
bx "
x!
$end
#5000
0$
0&
b0 3
b0 V
b0 1
b0 W
b0 0
b0 X
1#
1/
1%
12
1+
0,
b111111111 *
b111111111 Y
b111111111 (
b111111111 [
b0 '
b0 \
b0 )
b0 Z
0]
0!
b0 "
b0 ^
17
#10000
07
#15000
17
#20000
07
#25000
17
#30000
07
#35000
17
#40000
07
#45000
17
#50000
b0 a
b11 b
1H
07
#55000
bz (
bz [
bz '
bz \
bz )
bz Z
1!
0.
b1001 `
b1001 _
b1 a
1-
17
#60000
1.
0-
07
#65000
1!
0.
b1001 `
b1001 _
b10 a
1-
17
#70000
1.
0-
07
#75000
1!
0.
b1001 `
b1001 _
b10 b
b0 a
1-
17
#80000
1.
0-
07
#85000
1!
0.
b1001 `
b1001 _
b1 a
1-
17
#90000
1.
0-
07
#95000
1!
0.
b1001 `
b1001 _
b10 a
1-
17
#100000
1.
0-
07
#105000
1!
0.
b1001 `
b1001 _
1-
17
#106000
b0 a
b1 J
#110000
1.
0-
07
#115000
1!
0.
b1001 `
b1001 _
b1 a
1-
17
#120000
1.
0-
07
#125000
1!
0.
b1001 `
b1001 _
b10 a
1-
17
#130000
1.
0-
b11010101111001101 8
b11010101111001101 K
b10 :
b10 L
b1 ;
b1 M
1=
0?
09
1>
07
#135000
1!
b11010101111001101 3
b11010101111001101 V
b10 1
b10 W
b1 0
b1 X
02
0+
1,
0.
b1001 `
b1001 _
1-
17
#140000
1.
0-
07
#145000
1!
0.
b1001 `
b1001 _
1-
17
#146000
b10 J
#150000
1.
0-
b0 a
19
0>
07
#155000
1!
b0 3
b0 V
b0 1
b0 W
b0 0
b0 X
12
1+
0.
b1001 `
b1001 _
b1 a
1-
17
#160000
1.
0-
07
#165000
1!
0.
b1001 `
b1001 _
b10 a
1-
17
#170000
1.
0-
1R
b111111111 B
b111111111 P
b111111111 @
b111111111 N
b101001011010010110100101101001011010010110100101101001011010010110101010 A
b101001011010010110100101101001011010010110100101101001011010010110101010 O
07
#175000
b0 (
b0 [
b111111111 '
b111111111 \
b101001011010010110100101101001011010010110100101101001011010010110101010 )
b101001011010010110100101101001011010010110100101101001011010010110101010 Z
0!
1]
0.
b1001 `
b1001 _
1-
17
#180000
1.
0-
07
#185000
0.
b1001 `
b1001 _
1-
17
#186000
b0 a
b11 J
#190000
1.
0-
07
#195000
0.
b1001 `
b1001 _
b1 a
1-
17
#200000
1.
0-
07
#205000
0.
b1001 `
b1001 _
b10 a
1-
17
#210000
1.
0-
b100100011010001010110011110001001101010111100110111101111000000010010 G
b100100011010001010110011110001001101010111100110111101111000000010010 Q
0R
b0 B
b0 P
b0 @
b0 N
07
#215000
bz (
bz [
bz '
bz \
bz )
bz Z
1!
b100100011010001010110011110001001101010111100110111101111000000010010 "
b100100011010001010110011110001001101010111100110111101111000000010010 ^
0]
0.
b1001 `
b1001 _
1-
17
#220000
1.
0-
07
#225000
1!
0.
b1001 `
b1001 _
1-
17
#226000
b0 a
b100 J
#230000
1.
0-
07
#235000
1!
0.
b1001 `
b1001 _
b1 a
1-
17
#240000
1.
0-
07
#245000
1!
0.
b1001 `
b1001 _
b10 a
1-
17
#250000
1.
0-
1?
07
#255000
1!
0.
b1001 `
b1001 _
1-
17
#260000
1.
0-
07
#265000
1!
0.
b1001 `
b1001 _
1-
17
#266000
b0 a
b11 b
b101 J
#270000
1.
0-
07
#275000
1!
0.
b1001 `
b1001 _
b1 a
1-
17
#280000
1.
0-
07
#285000
1!
0.
b1001 `
b1001 _
b10 a
1-
17
#290000
1.
0-
07
#295000
1!
0.
b1001 `
b1001 _
b11 a
1-
17
#300000
1.
0-
1E
07
#305000
1$
1!
0.
b1001 `
b1001 _
1-
17
#310000
1.
0-
07
#315000
1!
0.
b1001 `
b1001 _
1-
17
#316000
b0 a
b110 J
#320000
1.
0-
07
#325000
1!
0.
b1001 `
b1001 _
b1 a
1-
17
#330000
1.
0-
07
#335000
1!
0.
b1001 `
b1001 _
b10 a
1-
17
#340000
1.
0-
07
#345000
1!
0.
b1001 `
b1001 _
b11 a
1-
17
