rtl/ddr4_refresh_ctrl.v
// DDR4 Refresh Controller
// tREFI countdown, FGR modes, per-bank refresh rotation, self-refresh entry/exit
module ddr4_refresh_ctrl #(
    parameter NUM_RANKS = 1
)(
    input  wire        clk,
    input  wire        rst_n,

    input  wire        init_done,
    input  wire [13:0] cfg_trefi,
    input  wire [1:0]  cfg_fgr_mode,  // 0=normal, 1=FGRx2, 2=FGRx4
    input  wire        cfg_pbr_en,

    output reg         ref_req,
    output reg  [1:0]  ref_rank,
    output reg  [3:0]  ref_bank,

    input  wire        ref_ack,
    input  wire        sr_req,
    output reg         sr_active,
    input  wire        sr_exit_req
);

    reg [13:0] trefi_cnt;
    reg [13:0] trefi_period;

    // Effective tREFI: divide by FGR mode
    always @(*) begin
        case (cfg_fgr_mode)
            2'd1: trefi_period = cfg_trefi >> 1;
            2'd2: trefi_period = cfg_trefi >> 2;
            default: trefi_period = cfg_trefi;
        endcase
    end

    // Self-refresh logic
    always @(posedge clk) begin
        if (!rst_n) begin
            sr_active <= 1'b0;
        end else begin
            if (sr_req && !sr_active)
                sr_active <= 1'b1;
            else if (sr_exit_req && sr_active)
                sr_active <= 1'b0;
        end
    end

    // tREFI countdown and ref_req generation
    always @(posedge clk) begin
        if (!rst_n) begin
            trefi_cnt <= 14'd0;
            ref_req   <= 1'b0;
            ref_rank  <= 2'd0;
            ref_bank  <= 4'd0;
        end else if (!init_done || sr_active) begin
            trefi_cnt <= trefi_period;
            ref_req   <= 1'b0;
        end else begin
            if (ref_req) begin
                // Hold until acked
                if (ref_ack) begin
                    ref_req   <= 1'b0;
                    trefi_cnt <= trefi_period;
                    // Rotate bank for PBR
                    if (cfg_pbr_en)
                        ref_bank <= ref_bank + 1;
                    else
                        ref_bank <= 4'd0;
                end
            end else begin
                if (trefi_cnt == 0 || trefi_cnt == 14'd1) begin
                    ref_req   <= 1'b1;
                    trefi_cnt <= trefi_period;
                end else begin
                    trefi_cnt <= trefi_cnt - 1;
                end
            end
        end
    end

endmodule

tb/ddr4_refresh_ctrl_tb.v
`timescale 1ns/1ps
module ddr4_refresh_ctrl_tb;

    reg        clk, rst_n;
    reg        init_done;
    reg [13:0] cfg_trefi;
    reg [1:0]  cfg_fgr_mode;
    reg        cfg_pbr_en;
    wire       ref_req;
    wire [1:0] ref_rank;
    wire [3:0] ref_bank;
    reg        ref_ack;
    reg        sr_req, sr_exit_req;
    wire       sr_active;

    ddr4_refresh_ctrl dut (
        .clk(clk), .rst_n(rst_n),
        .init_done(init_done),
        .cfg_trefi(cfg_trefi),
        .cfg_fgr_mode(cfg_fgr_mode),
        .cfg_pbr_en(cfg_pbr_en),
        .ref_req(ref_req),
        .ref_rank(ref_rank),
        .ref_bank(ref_bank),
        .ref_ack(ref_ack),
        .sr_req(sr_req),
        .sr_active(sr_active),
        .sr_exit_req(sr_exit_req)
    );

    initial clk = 0;
    always #5 clk = ~clk;

    initial begin
        $dumpfile("results/phase-core-ctrl/ddr4_refresh_ctrl.vcd");
        $dumpvars(0, ddr4_refresh_ctrl_tb);
    end

    integer wait_cnt;

    initial begin
        rst_n        = 0;
        init_done    = 0;
        cfg_trefi    = 14'd20;  // short period for sim
        cfg_fgr_mode = 2'd0;
        cfg_pbr_en   = 1'b0;
        ref_ack      = 0;
        sr_req       = 0;
        sr_exit_req  = 0;

        repeat(5) @(posedge clk);
        rst_n = 1;
        @(posedge clk);

        // Start refresh controller
        init_done = 1;

        // --- Test 1: Wait for ref_req ---
        $display("Test 1: waiting for ref_req");
        wait_cnt = 0;
        while (!ref_req) begin
            @(posedge clk);
            wait_cnt = wait_cnt + 1;
            if (wait_cnt >= 200)
                $fatal(1, "SIMULATION FAILED: ref_req not asserted within 200 cycles");
        end
        $display("ref_req asserted after %0d cycles", wait_cnt);

        // --- Test 2: ACK clears ref_req ---
        ref_ack = 1;
        @(posedge clk);
        ref_ack = 0;
        @(posedge clk);
        if (ref_req !== 1'b0)
            $fatal(1, "SIMULATION FAILED: ref_req should deassert after ack");
        $display("ref_req deasserted after ack");

        // --- Test 3: self-refresh entry ---
        $display("Test 3: self-refresh");
        sr_req = 1;
        @(posedge clk);
        @(posedge clk);
        if (!sr_active)
            $fatal(1, "SIMULATION FAILED: sr_active should be high after sr_req");
        $display("sr_active asserted");

        // While in self-refresh, ref_req should not assert
        repeat(30) @(posedge clk);
        if (ref_req)
            $fatal(1, "SIMULATION FAILED: ref_req should not assert during self-refresh");
        $display("ref_req suppressed during self-refresh");

        // --- Test 4: self-refresh exit ---
        sr_req      = 0;
        sr_exit_req = 1;
        @(posedge clk);
        sr_exit_req = 0;
        @(posedge clk);
        if (sr_active)
            $fatal(1, "SIMULATION FAILED: sr_active should deassert after exit_req");
        $display("sr_active deasserted");

        // --- Test 5: FGR×2 — period should halve ---
        // Re-init: reset and use FGR mode 1
        rst_n        = 0;
        init_done    = 0;
        cfg_fgr_mode = 2'd1;  // FGRx2
        cfg_pbr_en   = 1'b0;
        cfg_trefi    = 14'd20;
        ref_ack      = 0;
        repeat(4) @(posedge clk);
        rst_n     = 1;
        @(posedge clk);
        init_done = 1;

        $display("Test 5: FGRx2 mode — effective period = trefi/2 = 10");
        // With FGRx2, effective period = 20/2 = 10 cycles
        // ref_req must appear in <=15 cycles
        wait_cnt = 0;
        while (!ref_req) begin
            @(posedge clk);
            wait_cnt = wait_cnt + 1;
            if (wait_cnt >= 30)
                $fatal(1, "SIMULATION FAILED: FGRx2 ref_req not seen within 30 cycles");
        end
        if (wait_cnt > 15)
            $fatal(1, "SIMULATION FAILED: FGRx2 period too long (%0d), expected <=15", wait_cnt);
        $display("FGRx2 ref_req asserted after %0d cycles (OK, <=15)", wait_cnt);
        // ACK
        ref_ack = 1; @(posedge clk); ref_ack = 0; @(posedge clk);

        // --- Test 6: FGR×4 — period should quarter ---
        rst_n        = 0;
        init_done    = 0;
        cfg_fgr_mode = 2'd2;  // FGRx4
        cfg_trefi    = 14'd20;
        repeat(4) @(posedge clk);
        rst_n     = 1;
        @(posedge clk);
        init_done = 1;

        $display("Test 6: FGRx4 mode — effective period = trefi/4 = 5");
        wait_cnt = 0;
        while (!ref_req) begin
            @(posedge clk);
            wait_cnt = wait_cnt + 1;
            if (wait_cnt >= 20)
                $fatal(1, "SIMULATION FAILED: FGRx4 ref_req not seen within 20 cycles");
        end
        if (wait_cnt > 10)
            $fatal(1, "SIMULATION FAILED: FGRx4 period too long (%0d), expected <=10", wait_cnt);
        $display("FGRx4 ref_req asserted after %0d cycles (OK, <=10)", wait_cnt);
        ref_ack = 1; @(posedge clk); ref_ack = 0; @(posedge clk);

        // --- Test 7: PBR — bank rotates through all 16 banks ---
        rst_n        = 0;
        init_done    = 0;
        cfg_fgr_mode = 2'd0;
        cfg_pbr_en   = 1'b1;
        cfg_trefi    = 14'd10;
        repeat(4) @(posedge clk);
        rst_n     = 1;
        @(posedge clk);
        init_done = 1;

        $display("Test 7: PBR — bank rotates through all 16 banks");
        begin : pbr_loop
            integer b;
            for (b = 0; b < 16; b = b + 1) begin
                // Wait for ref_req
                wait_cnt = 0;
                @(posedge clk); // extra cycle so we don't exit immediately
                while (!ref_req) begin
                    @(posedge clk);
                    wait_cnt = wait_cnt + 1;
                    if (wait_cnt >= 50)
                        $fatal(1, "SIMULATION FAILED: PBR ref_req not seen (bank %0d)", b);
                end
                if (ref_bank !== b[3:0])
                    $fatal(1, "SIMULATION FAILED: PBR bank mismatch: got %0d expected %0d",
                               ref_bank, b);
                // Drive ACK on negedge to ensure RTL samples ref_ack=1 cleanly on next posedge
                @(negedge clk);
                ref_ack = 1;
                @(posedge clk);  // RTL sees ref_ack=1 → ACK fires (ref_bank++)
                @(negedge clk);
                ref_ack = 0;
            end
        end
        $display("PBR rotated through all 16 banks OK");

        $display("SIMULATION PASSED");
        $finish;
    end

endmodule

results/phase-core-ctrl/ddr4_refresh_ctrl.vcd
$date
	Thu Mar 12 11:24:20 2026
$end
$version
	Icarus Verilog
$end
$timescale
	1ps
$end
$scope module ddr4_refresh_ctrl_tb $end
$var wire 1 ! sr_active $end
$var wire 1 " ref_req $end
$var wire 2 # ref_rank [1:0] $end
$var wire 4 $ ref_bank [3:0] $end
$var reg 2 % cfg_fgr_mode [1:0] $end
$var reg 1 & cfg_pbr_en $end
$var reg 14 ' cfg_trefi [13:0] $end
$var reg 1 ( clk $end
$var reg 1 ) init_done $end
$var reg 1 * ref_ack $end
$var reg 1 + rst_n $end
$var reg 1 , sr_exit_req $end
$var reg 1 - sr_req $end
$var integer 32 . wait_cnt [31:0] $end
$scope module dut $end
$var wire 2 / cfg_fgr_mode [1:0] $end
$var wire 1 & cfg_pbr_en $end
$var wire 14 0 cfg_trefi [13:0] $end
$var wire 1 ( clk $end
$var wire 1 ) init_done $end
$var wire 1 * ref_ack $end
$var wire 1 + rst_n $end
$var wire 1 , sr_exit_req $end
$var wire 1 - sr_req $end
$var parameter 32 1 NUM_RANKS $end
$var reg 4 2 ref_bank [3:0] $end
$var reg 2 3 ref_rank [1:0] $end
$var reg 1 " ref_req $end
$var reg 1 ! sr_active $end
$var reg 14 4 trefi_cnt [13:0] $end
$var reg 14 5 trefi_period [13:0] $end
$upscope $end
$scope begin pbr_loop $end
$var integer 32 6 b [31:0] $end
$upscope $end
$upscope $end
$enddefinitions $end
$comment Show the parameter values. $end
$dumpall
b1 1
$end
#0
$dumpvars
bx 6
b10100 5
bx 4
bx 3
bx 2
b10100 0
b0 /
bx .
0-
0,
0+
0*
0)
0(
b10100 '
0&
b0 %
bx $
bx #
x"
x!
$end
#5000
0!
b0 $
b0 2
b0 #
b0 3
0"
b0 4
1(
#10000
0(
#15000
1(
#20000
0(
#25000
1(
#30000
0(
#35000
1(
#40000
0(
#45000
b10100 4
1+
1(
#50000
0(
#55000
b0 .
1)
1(
#60000
0(
#65000
b10011 4
b1 .
1(
#70000
0(
#75000
b10010 4
b10 .
1(
#80000
0(
#85000
b10001 4
b11 .
1(
#90000
0(
#95000
b10000 4
b100 .
1(
#100000
0(
#105000
b1111 4
b101 .
1(
#110000
0(
#115000
b1110 4
b110 .
1(
#120000
0(
#125000
b1101 4
b111 .
1(
#130000
0(
#135000
b1100 4
b1000 .
1(
#140000
0(
#145000
b1011 4
b1001 .
1(
#150000
0(
#155000
b1010 4
b1010 .
1(
#160000
0(
#165000
b1001 4
b1011 .
1(
#170000
0(
#175000
b1000 4
b1100 .
1(
#180000
0(
#185000
b111 4
b1101 .
1(
#190000
0(
#195000
b110 4
b1110 .
1(
#200000
0(
#205000
b101 4
b1111 .
1(
#210000
0(
#215000
b100 4
b10000 .
1(
#220000
0(
#225000
b11 4
b10001 .
1(
#230000
0(
#235000
b10 4
b10010 .
1(
#240000
0(
#245000
b1 4
b10011 .
1(
#250000
0(
#255000
b10100 4
1"
b10100 .
1(
#260000
0(
#265000
0"
1*
b10101 .
1(
#270000
0(
#275000
b10011 4
0*
1(
#280000
0(
#285000
1!
b10010 4
1-
1(
#290000
0(
#295000
b10100 4
1(
