rtl/ddr4_timing_engine.v
// DDR4 Timing Engine — per-bank/rank down-counters for all 16 JEDEC constraints
// timing_ok[i] = 1 when counter[i] == 0 (constraint satisfied)
module ddr4_timing_engine #(
    parameter NUM_BANKS   = 16,
    parameter NUM_BG      = 4,
    parameter tRCD_DEF    = 11,
    parameter tRP_DEF     = 11,
    parameter tRAS_DEF    = 28,
    parameter tRC_DEF     = 39,
    parameter tCCD_L_DEF  = 6,
    parameter tCCD_S_DEF  = 4,
    parameter tRRD_L_DEF  = 6,
    parameter tRRD_S_DEF  = 4,
    parameter tWR_DEF     = 15,
    parameter tWTR_L_DEF  = 12,
    parameter tWTR_S_DEF  = 4,
    parameter tRTP_DEF    = 6,
    parameter tFAW_DEF    = 16,
    parameter tRFC_DEF    = 420,
    parameter tMOD_DEF    = 24,
    parameter tZQ_DEF     = 64
)(
    input  wire        clk,
    input  wire        rst_n,

    input  wire        dram_cmd_valid,
    input  wire [2:0]  dram_cmd_type,
    input  wire [1:0]  dram_rank,
    input  wire [1:0]  dram_bg,
    input  wire [1:0]  dram_ba,

    input  wire [4:0]  cfg_cl,
    input  wire [4:0]  cfg_cwl,
    input  wire [7:0]  cfg_trcd,
    input  wire [7:0]  cfg_trp,
    input  wire [7:0]  cfg_tras,
    input  wire [7:0]  cfg_trc,
    input  wire [9:0]  cfg_trfc,
    input  wire [13:0] cfg_trefi,

    output wire [15:0] timing_ok
);

    // timing_ok bit indices
    localparam T_RCD   = 0;
    localparam T_RP    = 1;
    localparam T_RAS   = 2;
    localparam T_RC    = 3;
    localparam T_CCD_L = 4;
    localparam T_CCD_S = 5;
    localparam T_RRD_L = 6;
    localparam T_RRD_S = 7;
    localparam T_WR    = 8;
    localparam T_WTR_L = 9;
    localparam T_WTR_S = 10;
    localparam T_RTP   = 11;
    localparam T_FAW   = 12;
    localparam T_RFC   = 13;
    localparam T_MOD   = 14;
    localparam T_ZQ    = 15;

    // Command type encoding
    localparam CMD_NOP  = 3'd0;
    localparam CMD_MRS  = 3'd1;
    localparam CMD_REF  = 3'd2;
    localparam CMD_PRE  = 3'd3;
    localparam CMD_ACT  = 3'd4;
    localparam CMD_WR   = 3'd5;
    localparam CMD_RD   = 3'd6;
    localparam CMD_ZQCL = 3'd7;

    // Bank index from bg/ba
    wire [3:0] bank_idx = {dram_bg, dram_ba};

    // Per-bank counters (addressed by {bg,ba} = 4 bits = 16 banks)
    reg [7:0]  cnt_rcd [0:15];
    reg [7:0]  cnt_rp  [0:15];
    reg [7:0]  cnt_ras [0:15];
    reg [7:0]  cnt_rc  [0:15];
    reg [7:0]  cnt_rtp [0:15];
    reg [7:0]  cnt_wr  [0:15];

    // Rank-level counters
    reg [9:0]  cnt_rfc;
    reg [7:0]  cnt_faw;
    reg [7:0]  cnt_rrd_l;
    reg [7:0]  cnt_rrd_s;
    reg [7:0]  cnt_ccd_l;
    reg [7:0]  cnt_ccd_s;
    reg [7:0]  cnt_wtr_l;
    reg [7:0]  cnt_wtr_s;
    reg [7:0]  cnt_mod;
    reg [7:0]  cnt_zq;

    // Effective timing values (use cfg if nonzero, else defaults)
    wire [7:0]  trcd_val  = (cfg_trcd  != 0) ? cfg_trcd  : tRCD_DEF[7:0];
    wire [7:0]  trp_val   = (cfg_trp   != 0) ? cfg_trp   : tRP_DEF[7:0];
    wire [7:0]  tras_val  = (cfg_tras  != 0) ? cfg_tras  : tRAS_DEF[7:0];
    wire [7:0]  trc_val   = (cfg_trc   != 0) ? cfg_trc   : tRC_DEF[7:0];
    wire [9:0]  trfc_val  = (cfg_trfc  != 0) ? cfg_trfc  : tRFC_DEF[9:0];

    integer i;

    always @(posedge clk) begin
        if (!rst_n) begin
            for (i = 0; i < 16; i = i + 1) begin
                cnt_rcd[i] <= 8'd0;
                cnt_rp[i]  <= 8'd0;
                cnt_ras[i] <= 8'd0;
                cnt_rc[i]  <= 8'd0;
                cnt_rtp[i] <= 8'd0;
                cnt_wr[i]  <= 8'd0;
            end
            cnt_rfc   <= 10'd0;
            cnt_faw   <= 8'd0;
            cnt_rrd_l <= 8'd0;
            cnt_rrd_s <= 8'd0;
            cnt_ccd_l <= 8'd0;
            cnt_ccd_s <= 8'd0;
            cnt_wtr_l <= 8'd0;
            cnt_wtr_s <= 8'd0;
            cnt_mod   <= 8'd0;
            cnt_zq    <= 8'd0;
        end else begin
            // Decrement all non-zero counters
            for (i = 0; i < 16; i = i + 1) begin
                if (cnt_rcd[i] != 0) cnt_rcd[i] <= cnt_rcd[i] - 1;
                if (cnt_rp[i]  != 0) cnt_rp[i]  <= cnt_rp[i]  - 1;
                if (cnt_ras[i] != 0) cnt_ras[i] <= cnt_ras[i] - 1;
                if (cnt_rc[i]  != 0) cnt_rc[i]  <= cnt_rc[i]  - 1;
                if (cnt_rtp[i] != 0) cnt_rtp[i] <= cnt_rtp[i] - 1;
                if (cnt_wr[i]  != 0) cnt_wr[i]  <= cnt_wr[i]  - 1;
            end
            if (cnt_rfc   != 0) cnt_rfc   <= cnt_rfc   - 1;
            if (cnt_faw   != 0) cnt_faw   <= cnt_faw   - 1;
            if (cnt_rrd_l != 0) cnt_rrd_l <= cnt_rrd_l - 1;
            if (cnt_rrd_s != 0) cnt_rrd_s <= cnt_rrd_s - 1;
            if (cnt_ccd_l != 0) cnt_ccd_l <= cnt_ccd_l - 1;
            if (cnt_ccd_s != 0) cnt_ccd_s <= cnt_ccd_s - 1;
            if (cnt_wtr_l != 0) cnt_wtr_l <= cnt_wtr_l - 1;
            if (cnt_wtr_s != 0) cnt_wtr_s <= cnt_wtr_s - 1;
            if (cnt_mod   != 0) cnt_mod   <= cnt_mod   - 1;
            if (cnt_zq    != 0) cnt_zq    <= cnt_zq    - 1;

            // Load counters on valid command
            if (dram_cmd_valid) begin
                case (dram_cmd_type)
                    CMD_ACT: begin
                        cnt_rcd[bank_idx] <= trcd_val;
                        cnt_ras[bank_idx] <= tras_val;
                        cnt_rc[bank_idx]  <= trc_val;
                        cnt_rrd_l         <= tRRD_L_DEF[7:0];
                        cnt_rrd_s         <= tRRD_S_DEF[7:0];
                        cnt_faw           <= tFAW_DEF[7:0];
                    end
                    CMD_RD: begin
                        cnt_ccd_l         <= tCCD_L_DEF[7:0];
                        cnt_ccd_s         <= tCCD_S_DEF[7:0];
                        cnt_rtp[bank_idx] <= tRTP_DEF[7:0];
                    end
                    CMD_WR: begin
                        cnt_ccd_l         <= tCCD_L_DEF[7:0];
                        cnt_ccd_s         <= tCCD_S_DEF[7:0];
                        cnt_wr[bank_idx]  <= tWR_DEF[7:0];
                        cnt_wtr_l         <= tWTR_L_DEF[7:0];
                        cnt_wtr_s         <= tWTR_S_DEF[7:0];
                    end
                    CMD_PRE: begin
                        cnt_rp[bank_idx]  <= trp_val;
                    end
                    CMD_REF: begin
                        cnt_rfc           <= trfc_val;
                    end
                    CMD_MRS: begin
                        cnt_mod           <= tMOD_DEF[7:0];
                    end
                    CMD_ZQCL: begin
                        cnt_zq            <= tZQ_DEF[7:0];
                    end
                    default: begin end
                endcase
            end
        end
    end

    // timing_ok[i] = 1 when counter is 0 (constraint met)
    // Report status for the addressed bank
    assign timing_ok[T_RCD]   = (cnt_rcd[bank_idx] == 0);
    assign timing_ok[T_RP]    = (cnt_rp[bank_idx]  == 0);
    assign timing_ok[T_RAS]   = (cnt_ras[bank_idx] == 0);
    assign timing_ok[T_RC]    = (cnt_rc[bank_idx]  == 0);
    assign timing_ok[T_CCD_L] = (cnt_ccd_l == 0);
    assign timing_ok[T_CCD_S] = (cnt_ccd_s == 0);
    assign timing_ok[T_RRD_L] = (cnt_rrd_l == 0);
    assign timing_ok[T_RRD_S] = (cnt_rrd_s == 0);
    assign timing_ok[T_WR]    = (cnt_wr[bank_idx]  == 0);
    assign timing_ok[T_WTR_L] = (cnt_wtr_l == 0);
    assign timing_ok[T_WTR_S] = (cnt_wtr_s == 0);
    assign timing_ok[T_RTP]   = (cnt_rtp[bank_idx] == 0);
    assign timing_ok[T_FAW]   = (cnt_faw   == 0);
    assign timing_ok[T_RFC]   = (cnt_rfc   == 0);
    assign timing_ok[T_MOD]   = (cnt_mod   == 0);
    assign timing_ok[T_ZQ]    = (cnt_zq    == 0);

endmodule

tb/ddr4_timing_engine_tb.v
`timescale 1ns/1ps
module ddr4_timing_engine_tb;

    reg         clk, rst_n;
    reg         dram_cmd_valid;
    reg [2:0]   dram_cmd_type;
    reg [1:0]   dram_rank, dram_bg, dram_ba;
    reg [4:0]   cfg_cl, cfg_cwl;
    reg [7:0]   cfg_trcd, cfg_trp, cfg_tras, cfg_trc;
    reg [9:0]   cfg_trfc;
    reg [13:0]  cfg_trefi;
    wire [15:0] timing_ok;

    // Use small timing parameters for simulation speed
    ddr4_timing_engine #(
        .tRCD_DEF(5), .tRP_DEF(5), .tRAS_DEF(10),
        .tRC_DEF(15), .tCCD_L_DEF(4), .tCCD_S_DEF(2),
        .tRRD_L_DEF(4), .tRRD_S_DEF(2),
        .tWR_DEF(8), .tWTR_L_DEF(6), .tWTR_S_DEF(2),
        .tRTP_DEF(4), .tFAW_DEF(8), .tRFC_DEF(20),
        .tMOD_DEF(6), .tZQ_DEF(10)
    ) dut (
        .clk(clk), .rst_n(rst_n),
        .dram_cmd_valid(dram_cmd_valid),
        .dram_cmd_type(dram_cmd_type),
        .dram_rank(dram_rank),
        .dram_bg(dram_bg), .dram_ba(dram_ba),
        .cfg_cl(cfg_cl), .cfg_cwl(cfg_cwl),
        .cfg_trcd(cfg_trcd), .cfg_trp(cfg_trp),
        .cfg_tras(cfg_tras), .cfg_trc(cfg_trc),
        .cfg_trfc(cfg_trfc), .cfg_trefi(cfg_trefi),
        .timing_ok(timing_ok)
    );

    initial clk = 0;
    always #5 clk = ~clk;

    initial begin
        $dumpfile("results/phase-core-ctrl/ddr4_timing_engine.vcd");
        $dumpvars(0, ddr4_timing_engine_tb);
    end

    task send_cmd;
        input [2:0] ctype;
        input [1:0] bg, ba;
        begin
            @(posedge clk);
            dram_cmd_valid = 1'b1;
            dram_cmd_type  = ctype;
            dram_bg        = bg;
            dram_ba        = ba;
            @(posedge clk);
            dram_cmd_valid = 1'b0;
        end
    endtask

    integer i;

    initial begin
        rst_n           = 0;
        dram_cmd_valid  = 0;
        dram_cmd_type   = 0;
        dram_rank       = 0;
        dram_bg         = 0;
        dram_ba         = 0;
        cfg_cl          = 5'd11;
        cfg_cwl         = 5'd9;
        cfg_trcd        = 8'd0;  // use defaults
        cfg_trp         = 8'd0;
        cfg_tras        = 8'd0;
        cfg_trc         = 8'd0;
        cfg_trfc        = 10'd0;
        cfg_trefi       = 14'd0;

        repeat(5) @(posedge clk);
        rst_n = 1;
        @(posedge clk);

        // --- Test 1: ACT causes tRCD to deassert ---
        $display("Test 1: ACT -> tRCD");
        send_cmd(3'd4, 2'd0, 2'd0); // ACT bank 0

        // tRCD counter should be loaded; timing_ok[0] should be 0
        @(posedge clk);
        if (timing_ok[0] !== 1'b0)
            $fatal(1, "SIMULATION FAILED: tRCD should be busy after ACT (got %b)", timing_ok[0]);

        // Wait for tRCD to expire (tRCD_DEF=5 + margin)
        repeat(10) @(posedge clk);
        if (timing_ok[0] !== 1'b1)
            $fatal(1, "SIMULATION FAILED: tRCD should be OK after wait");
        $display("tRCD recovered correctly");

        // --- Test 2: PRE causes tRP ---
        $display("Test 2: PRE -> tRP");
        send_cmd(3'd3, 2'd0, 2'd0); // PRE bank 0

        @(posedge clk);
        if (timing_ok[1] !== 1'b0)
            $fatal(1, "SIMULATION FAILED: tRP should be busy after PRE");

        repeat(10) @(posedge clk);
        if (timing_ok[1] !== 1'b1)
            $fatal(1, "SIMULATION FAILED: tRP should be OK after wait");
        $display("tRP recovered correctly");

        // --- Test 3: REF causes tRFC ---
        $display("Test 3: REF -> tRFC");
        send_cmd(3'd2, 2'd0, 2'd0); // REF

        @(posedge clk);
        if (timing_ok[13] !== 1'b0)
            $fatal(1, "SIMULATION FAILED: tRFC should be busy after REF");

        // Wait for tRFC (tRFC_DEF=20 + margin)
        repeat(30) @(posedge clk);
        if (timing_ok[13] !== 1'b1)
            $fatal(1, "SIMULATION FAILED: tRFC should be OK after wait");
        $display("tRFC recovered correctly");

        $display("SIMULATION PASSED");
        $finish;
    end

endmodule

results/phase-core-ctrl/ddr4_timing_engine.vcd
$date
	Thu Mar 12 11:25:54 2026
$end
$version
	Icarus Verilog
$end
$timescale
	1ps
$end
$scope module ddr4_timing_engine_tb $end
$var wire 16 ! timing_ok [15:0] $end
$var reg 5 " cfg_cl [4:0] $end
$var reg 5 # cfg_cwl [4:0] $end
$var reg 8 $ cfg_tras [7:0] $end
$var reg 8 % cfg_trc [7:0] $end
$var reg 8 & cfg_trcd [7:0] $end
$var reg 14 ' cfg_trefi [13:0] $end
$var reg 10 ( cfg_trfc [9:0] $end
$var reg 8 ) cfg_trp [7:0] $end
$var reg 1 * clk $end
$var reg 2 + dram_ba [1:0] $end
$var reg 2 , dram_bg [1:0] $end
$var reg 3 - dram_cmd_type [2:0] $end
$var reg 1 . dram_cmd_valid $end
$var reg 2 / dram_rank [1:0] $end
$var reg 1 0 rst_n $end
$scope module dut $end
$var wire 5 1 cfg_cl [4:0] $end
$var wire 5 2 cfg_cwl [4:0] $end
$var wire 8 3 cfg_tras [7:0] $end
$var wire 8 4 cfg_trc [7:0] $end
$var wire 8 5 cfg_trcd [7:0] $end
$var wire 14 6 cfg_trefi [13:0] $end
$var wire 10 7 cfg_trfc [9:0] $end
$var wire 8 8 cfg_trp [7:0] $end
$var wire 1 * clk $end
$var wire 2 9 dram_ba [1:0] $end
$var wire 2 : dram_bg [1:0] $end
$var wire 3 ; dram_cmd_type [2:0] $end
$var wire 1 . dram_cmd_valid $end
$var wire 2 < dram_rank [1:0] $end
$var wire 1 0 rst_n $end
$var wire 8 = trp_val [7:0] $end
$var wire 10 > trfc_val [9:0] $end
$var wire 8 ? trcd_val [7:0] $end
$var wire 8 @ trc_val [7:0] $end
$var wire 8 A tras_val [7:0] $end
$var wire 16 B timing_ok [15:0] $end
$var wire 4 C bank_idx [3:0] $end
$var parameter 3 D CMD_ACT $end
$var parameter 3 E CMD_MRS $end
$var parameter 3 F CMD_NOP $end
$var parameter 3 G CMD_PRE $end
$var parameter 3 H CMD_RD $end
$var parameter 3 I CMD_REF $end
$var parameter 3 J CMD_WR $end
$var parameter 3 K CMD_ZQCL $end
$var parameter 32 L NUM_BANKS $end
$var parameter 32 M NUM_BG $end
$var parameter 32 N T_CCD_L $end
$var parameter 32 O T_CCD_S $end
$var parameter 32 P T_FAW $end
$var parameter 32 Q T_MOD $end
$var parameter 32 R T_RAS $end
$var parameter 32 S T_RC $end
$var parameter 32 T T_RCD $end
$var parameter 32 U T_RFC $end
$var parameter 32 V T_RP $end
$var parameter 32 W T_RRD_L $end
$var parameter 32 X T_RRD_S $end
$var parameter 32 Y T_RTP $end
$var parameter 32 Z T_WR $end
$var parameter 32 [ T_WTR_L $end
$var parameter 32 \ T_WTR_S $end
$var parameter 32 ] T_ZQ $end
$var parameter 32 ^ tCCD_L_DEF $end
$var parameter 32 _ tCCD_S_DEF $end
$var parameter 32 ` tFAW_DEF $end
$var parameter 32 a tMOD_DEF $end
$var parameter 32 b tRAS_DEF $end
$var parameter 32 c tRCD_DEF $end
$var parameter 32 d tRC_DEF $end
$var parameter 32 e tRFC_DEF $end
$var parameter 32 f tRP_DEF $end
$var parameter 32 g tRRD_L_DEF $end
$var parameter 32 h tRRD_S_DEF $end
$var parameter 32 i tRTP_DEF $end
$var parameter 32 j tWR_DEF $end
$var parameter 32 k tWTR_L_DEF $end
$var parameter 32 l tWTR_S_DEF $end
$var parameter 32 m tZQ_DEF $end
$var reg 8 n cnt_ccd_l [7:0] $end
$var reg 8 o cnt_ccd_s [7:0] $end
$var reg 8 p cnt_faw [7:0] $end
$var reg 8 q cnt_mod [7:0] $end
$var reg 10 r cnt_rfc [9:0] $end
$var reg 8 s cnt_rrd_l [7:0] $end
$var reg 8 t cnt_rrd_s [7:0] $end
$var reg 8 u cnt_wtr_l [7:0] $end
$var reg 8 v cnt_wtr_s [7:0] $end
$var reg 8 w cnt_zq [7:0] $end
$var integer 32 x i [31:0] $end
$upscope $end
$scope task send_cmd $end
$var reg 2 y ba [1:0] $end
$var reg 2 z bg [1:0] $end
$var reg 3 { ctype [2:0] $end
$upscope $end
$upscope $end
$enddefinitions $end
$comment Show the parameter values. $end
$dumpall
b1010 m
b10 l
b110 k
b1000 j
b100 i
b10 h
b100 g
b101 f
b10100 e
b1111 d
b101 c
b1010 b
b110 a
b1000 `
b10 _
b100 ^
b1111 ]
b1010 \
b1001 [
b1000 Z
b1011 Y
b111 X
b110 W
b1 V
b1101 U
b0 T
b11 S
b10 R
b1110 Q
b1100 P
b101 O
b100 N
b100 M
b10000 L
b111 K
b101 J
b10 I
b110 H
b11 G
b0 F
b1 E
b100 D
$end
#0
$dumpvars
bx {
bx z
bx y
bx x
bx w
bx v
bx u
bx t
bx s
bx r
bx q
bx p
bx o
bx n
b0 C
bx B
b1010 A
b1111 @
b101 ?
b10100 >
b101 =
b0 <
b0 ;
b0 :
b0 9
b0 8
b0 7
b0 6
b0 5
b0 4
b0 3
b1001 2
b1011 1
00
b0 /
0.
b0 -
b0 ,
b0 +
0*
b0 )
b0 (
b0 '
b0 &
b0 %
b0 $
b1001 #
b1011 "
bx !
$end
#5000
b0 w
b0 q
b0 v
b0 u
b0 o
b0 n
b0 t
b0 s
b0 p
b0 r
b1111111111111111 !
b1111111111111111 B
b10000 x
1*
#10000
0*
#15000
b10000 x
1*
#20000
0*
#25000
b10000 x
1*
#30000
0*
#35000
b10000 x
1*
#40000
0*
#45000
b10000 x
10
1*
#50000
0*
#55000
b0 y
b0 z
b100 {
b10000 x
1*
#60000
0*
#65000
b1000 p
b10 t
b100 s
b1110111100110010 !
b1110111100110010 B
b10000 x
b100 -
b100 ;
1.
1*
#70000
0*
#75000
b10 t
b100 s
b1000 p
0.
b10000 x
1*
#80000
0*
#85000
b1 t
b11 s
b111 p
b10000 x
1*
#90000
0*
#95000
b1110111110110010 !
b1110111110110010 B
b0 t
b10 s
b110 p
b10000 x
1*
#100000
0*
#105000
b1 s
b101 p
b10000 x
1*
#110000
0*
#115000
b1110111111110010 !
b1110111111110010 B
b0 s
b100 p
b10000 x
1*
#120000
0*
#125000
b11 p
b1110111111110011 !
b1110111111110011 B
b10000 x
1*
#130000
0*
#135000
b10 p
b10000 x
1*
#140000
0*
#145000
b1 p
b10000 x
1*
#150000
0*
#155000
b1111111111110011 !
b1111111111110011 B
b0 p
b10000 x
1*
#160000
0*
#165000
b10000 x
1*
#170000
0*
#175000
b1111111111110111 !
b1111111111110111 B
b10000 x
1*
#180000
0*
#185000
b10000 x
b11 {
1*
#190000
0*
#195000
b1111111111110101 !
b1111111111110101 B
b10000 x
b11 -
b11 ;
1.
1*
#200000
0*
#205000
0.
b10000 x
1*
#210000
0*
#215000
b10000 x
1*
#220000
0*
#225000
b1111111111111101 !
b1111111111111101 B
b10000 x
1*
#230000
0*
#235000
b10000 x
1*
#240000
0*
#245000
b10000 x
1*
#250000
0*
#255000
b1111111111111111 !
b1111111111111111 B
b10000 x
1*
#260000
0*
#265000
b10000 x
1*
#270000
0*
#275000
b10000 x
1*
#280000
0*
#285000
b10000 x
1*
#290000
0*
#295000
b10000 x
1*
#300000
0*
#305000
b10000 x
1*
#310000
0*
#315000
b10000 x
b10 {
1*
#320000
0*
#325000
b1101111111111111 !
b1101111111111111 B
b10100 r
b10000 x
b10 -
b10 ;
1.
1*
#330000
0*
#335000
b10100 r
0.
b10000 x
1*
#340000
0*
#345000
b10011 r
b10000 x
1*
#350000
0*
#355000
b10010 r
b10000 x
1*
#360000
0*
#365000
b10001 r
b10000 x
1*
#370000
0*
#375000
b10000 r
b10000 x
1*
#380000
0*
#385000
b1111 r
b10000 x
1*
#390000
0*
#395000
b1110 r
b10000 x
1*
#400000
0*
#405000
b1101 r
b10000 x
1*
#410000
0*
#415000
b1100 r
b10000 x
1*
#420000
0*
#425000
b1011 r
b10000 x
1*
#430000
0*
#435000
b1010 r
b10000 x
1*
#440000
0*
#445000
b1001 r
b10000 x
1*
#450000
0*
#455000
b1000 r
b10000 x
1*
#460000
0*
#465000
b111 r
b10000 x
1*
#470000
0*
#475000
b110 r
b10000 x
1*
#480000
0*
#485000
b101 r
b10000 x
1*
#490000
0*
#495000
b100 r
b10000 x
1*
#500000
0*
#505000
b11 r
b10000 x
1*
#510000
0*
#515000
b10 r
b10000 x
1*
#520000
0*
#525000
b1 r
b10000 x
1*
#530000
0*
#535000
b1111111111111111 !
b1111111111111111 B
b0 r
b10000 x
1*
#540000
0*
#545000
b10000 x
1*
#550000
0*
#555000
b10000 x
1*
#560000
0*
#565000
b10000 x
1*
#570000
0*
#575000
b10000 x
1*
#580000
0*
#585000
b10000 x
1*
#590000
0*
#595000
b10000 x
1*
#600000
0*
#605000
b10000 x
1*
#610000
0*
#615000
b10000 x
1*
#620000
0*
#625000
b10000 x
1*
#630000
0*
#635000
b10000 x
1*
#640000
0*
#645000
b10000 x
b100 {
1*
#650000
0*
#655000
b1000 p
b10 t
b100 s
b1110111100110010 !
b1110111100110010 B
b10000 x
b100 -
b100 ;
1.
1*
#660000
0*
#665000
b10 t
b100 s
b1000 p
0.
b10000 x
1*
#670000
0*
#675000
b1 t
b11 s
b111 p
b10000 x
1*
#680000
0*
#685000
b1110111110110010 !
b1110111110110010 B
b0 t
b10 s
b110 p
b10000 x
1*
#690000
0*
#695000
b1 s
b101 p
b10000 x
1*
#700000
0*
#705000
b1110111111110010 !
b1110111111110010 B
b0 s
b100 p
b10000 x
1*
#710000
0*
#715000
b11 p
b1110111111110011 !
b1110111111110011 B
b10000 x
1*
#720000
0*
#725000
b10 p
b10000 x
1*
#730000
0*
#735000
b1 p
b10000 x
1*
#740000
0*
#745000
b1111111111110011 !
b1111111111110011 B
b0 p
b10000 x
1*
#750000
0*
#755000
b10000 x
1*
#760000
0*
#765000
b1111111111110111 !
b1111111111110111 B
b10000 x
1*
#770000
0*
#775000
b10000 x
1*
#780000
0*
#785000
b10000 x
1*
#790000
0*
#795000
b10000 x
1*
#800000
0*
#805000
b10000 x
1*
#810000
0*
#815000
b1111111111111111 !
b1111111111111111 B
b10000 x
1*
#820000
0*
#825000
b10000 x
1*
#830000
0*
#835000
b10000 x
1*
#840000
0*
#845000
b10000 x
1*
#850000
0*
#855000
b10000 x
1*
#860000
0*
#865000
b10000 x
1*
#870000
0*
#875000
b10000 x
1*
#880000
0*
#885000
b1000 p
b10 t
b100 s
b1110111100110010 !
b1110111100110010 B
b10000 x
1.
1*
#890000
0*
#895000
b10 t
b100 s
b1000 p
0.
b10000 x
1*
#900000
0*
#905000
b1 t
b11 s
b111 p
b10000 x
b1 z
1*
#910000
0*
#915000
b10 t
b100 s
b1000 p
b10000 x
b1110111100110010 !
b1110111100110010 B
b100 C
b1 ,
b1 :
1.
1*
#920000
0*
#925000
b10 t
b100 s
b1000 p
0.
b10000 x
1*
#930000
0*
#935000
b1 t
b11 s
b111 p
b10000 x
1*
#940000
0*
#945000
b1110111110110010 !
b1110111110110010 B
b0 t
b10 s
b110 p
b10000 x
1*
#950000
0*
#955000
b1 s
b101 p
b10000 x
1*
#960000
0*
#965000
b1110111111110010 !
b1110111111110010 B
b0 s
b100 p
b10000 x
1*
#970000
0*
#975000
b11 p
b1110111111110011 !
b1110111111110011 B
b10000 x
1*
#980000
0*
#985000
b10 p
b10000 x
1*
#990000
0*
#995000
b1 p
b10000 x
1*
#1000000
0*
#1005000
b1111111111110011 !
b1111111111110011 B
b0 p
b10000 x
1*
#1010000
0*
#1015000
b10000 x
1*
#1020000
0*
#1025000
b1111111111110111 !
b1111111111110111 B
b10000 x
1*
#1030000
0*
#1035000
b10000 x
b0 z
b101 {
1*
#1040000
0*
#1045000
b10 v
b110 u
b10 o
b100 n
b1111100011001111 !
b1111100011001111 B
b10000 x
b0 C
b0 ,
b0 :
b101 -
b101 ;
1.
1*
#1050000
0*
#1055000
b10 v
b110 u
b10 o
b100 n
0.
b10000 x
1*
#1060000
0*
#1065000
b1 v
b101 u
b1 o
b11 n
b10000 x
1*
#1070000
0*
#1075000
b0 v
b100 u
b1111110011101111 !
b1111110011101111 B
b0 o
b10 n
b10000 x
1*
#1080000
0*
#1085000
b11 u
b1 n
b10000 x
1*
#1090000
0*
#1095000
b10 u
b1111110011111111 !
b1111110011111111 B
b0 n
b10000 x
1*
#1100000
0*
#1105000
b1 u
b10000 x
1*
#1110000
0*
#1115000
b1111111011111111 !
b1111111011111111 B
b0 u
b10000 x
1*
#1120000
0*
#1125000
b10000 x
1*
#1130000
0*
#1135000
b1111111111111111 !
b1111111111111111 B
b10000 x
1*
#1140000
0*
#1145000
b10000 x
1*
#1150000
0*
#1155000
b10000 x
1*
#1160000
0*
#1165000
b10000 x
1*
#1170000
0*
#1175000
b10000 x
1*
#1180000
0*
#1185000
b10000 x
1*
#1190000
0*
#1195000
b10000 x
1*
#1200000
0*
#1205000
b10000 x
1*
#1210000
0*
#1215000
b10000 x
1*
#1220000
0*
#1225000
b10000 x
1*
#1230000
0*
#1235000
b10000 x
1*
#1240000
0*
#1245000
b10000 x
1*
#1250000
0*
#1255000
b10000 x
1*
#1260000
0*
#1265000
b10000 x
b110 {
1*
#1270000
0*
#1275000
b10 o
b1111011111001111 !
b1111011111001111 B
b100 n
b10000 x
b110 -
b110 ;
1.
1*
#1280000
0*
#1285000
b10 o
b100 n
0.
b10000 x
1*
#1290000
0*
#1295000
b1 o
b11 n
b10000 x
1*
#1300000
0*
#1305000
b1111011111101111 !
b1111011111101111 B
b0 o
b10 n
b10000 x
1*
#1310000
0*
#1315000
b1 n
b10000 x
1*
#1320000
0*
#1325000
b0 n
b1111111111111111 !
b1111111111111111 B
b10000 x
1*
#1330000
0*
#1335000
b10000 x
1*
#1340000
0*
#1345000
b10000 x
1*
#1350000
0*
#1355000
b10000 x
1*
#1360000
0*
#1365000
b10000 x
1*
#1370000
0*
#1375000
b10000 x
1*
#1380000
0*
#1385000
b10000 x
1*
#1390000
0*
#1395000
b10000 x
1*
#1400000
0*
#1405000
b10000 x
1*
#1410000
0*
#1415000
b10000 x
1*
#1420000
0*
#1425000
b10000 x
1*
#1430000
0*
#1435000
b10000 x
1*
#1440000
0*
#1445000
b1 {
b10000 x
1*
#1450000
0*
#1455000
b1011111111111111 !
b1011111111111111 B
b110 q
b10000 x
b1 -
b1 ;
1.
1*
#1460000
0*
#1465000
b110 q
0.
b10000 x
1*
#1470000
0*
#1475000
b101 q
b10000 x
1*
#1480000
0*
#1485000
b100 q
b10000 x
1*
#1490000
0*
#1495000
b11 q
b10000 x
1*
#1500000
0*
#1505000
b10 q
b10000 x
1*
#1510000
0*
#1515000
b1 q
b10000 x
1*
#1520000
0*
#1525000
b1111111111111111 !
b1111111111111111 B
b0 q
b10000 x
1*
#1530000
0*
#1535000
b10000 x
1*
#1540000
0*
#1545000
b10000 x
1*
#1550000
0*
#1555000
b10000 x
1*
#1560000
0*
#1565000
b10000 x
1*
#1570000
0*
#1575000
b10000 x
1*
#1580000
0*
#1585000
b10000 x
1*
#1590000
0*
#1595000
b10000 x
1*
#1600000
0*
#1605000
b10000 x
1*
#1610000
0*
#1615000
b10000 x
1*
#1620000
0*
#1625000
b111 {
b10000 x
1*
#1630000
0*
#1635000
b111111111111111 !
b111111111111111 B
b1010 w
b10000 x
b111 -
b111 ;
1.
1*
#1640000
0*
#1645000
b1010 w
0.
b10000 x
1*
#1650000
0*
#1655000
b1001 w
b10000 x
1*
#1660000
0*
#1665000
b1000 w
b10000 x
1*
#1670000
0*
#1675000
b111 w
b10000 x
1*
#1680000
0*
#1685000
b110 w
b10000 x
1*
#1690000
0*
#1695000
b101 w
b10000 x
1*
#1700000
0*
#1705000
b100 w
b10000 x
1*
#1710000
0*
#1715000
b11 w
b10000 x
1*
#1720000
0*
#1725000
b10 w
b10000 x
1*
#1730000
0*
#1735000
b1 w
b10000 x
1*
#1740000
0*
#1745000
b1111111111111111 !
b1111111111111111 B
b0 w
b10000 x
1*
#1750000
0*
#1755000
b10000 x
1*
#1760000
0*
#1765000
b10000 x
1*
#1770000
0*
#1775000
b10000 x
1*
#1780000
0*
#1785000
b10000 x
1*
#1790000
0*
#1795000
b10000 x
1*
#1800000
0*
#1805000
b10000 x
1*
#1810000
0*
#1815000
b10000 x
1*
#1820000
0*
#1825000
b10000 x
1*
#1830000
0*
#1835000
b10000 x
1*
#1840000
0*
#1845000
b10000 x
1*
#1850000
0*
#1855000
b10000 x
1*
