rtl/ddr4_mode_reg.v
// DDR4 Mode Register Shadow and MRS Payload Encoder
// Encodes cfg_* inputs into JEDEC DDR4 MR0-MR6 payload
module ddr4_mode_reg (
    input  wire        clk,
    input  wire        rst_n,

    // Configuration inputs
    input  wire [4:0]  cfg_cl,
    input  wire [4:0]  cfg_cwl,
    input  wire [1:0]  cfg_al,
    input  wire [2:0]  cfg_rtt_nom,
    input  wire [2:0]  cfg_rtt_wr,
    input  wire [2:0]  cfg_rtt_park,
    input  wire [1:0]  cfg_drive_strength,
    input  wire [3:0]  cfg_wr_recovery,
    input  wire        cfg_dbi_rd_en,
    input  wire        cfg_dbi_wr_en,
    input  wire        cfg_ca_parity_en,

    // MR access
    input  wire [2:0]  mr_select,
    output reg  [16:0] mr_data
);

    wire [16:0] mr0, mr1, mr2, mr3, mr4, mr5, mr6;

    // MR0: BL=BL8, CL, WR recovery (17 bits)
    // bit0=burst_type(0), bits[2:1]=BL(2'b00=BL8), bit3=0
    // bits[6:4]=CL[2:0], bit7=0, bit8=0
    // bits[11:9]=WR[2:0], bit12=CL[3], bit13=WR[3], bits[16:14]=0
    assign mr0 = {3'b000, cfg_wr_recovery[3], cfg_cl[3],
                  cfg_wr_recovery[2:0],
                  2'b00, cfg_cl[2:0],
                  1'b0, 2'b00, 1'b0};

    // MR1: drive_strength[1:0], AL[1:0], RTT_NOM[2:0]
    // bits[1:0]=drive, bits[4:3]=AL, bits[10:8]=RTT_NOM
    assign mr1 = {6'b000000, cfg_rtt_nom, 3'b000, cfg_al, 1'b0, cfg_drive_strength};

    // MR2: CWL encoding, RTT_WR
    // bits[5:3]=CWL-9 clamped, bits[11:9]=RTT_WR
    wire [2:0] cwl_enc = (cfg_cwl >= 5'd9) ? (cfg_cwl - 5'd9) : 3'd0;
    assign mr2 = {5'b00000, cfg_rtt_wr, 3'b000, cwl_enc, 3'b000};

    // MR3,MR4,MR6: reserved, return 0
    assign mr3 = 17'h0;
    assign mr4 = 17'h0;
    assign mr6 = 17'h0;

    // MR5: RTT_PARK, DBI, CA parity (17 bits)
    // bit0=CA_PARITY, bits[8:6]=RTT_PARK, bit11=DBI_WR, bit12=DBI_RD
    assign mr5 = {4'b0000, cfg_dbi_rd_en, cfg_dbi_wr_en, 2'b00,
                  cfg_rtt_park, 5'b00000, cfg_ca_parity_en};

    always @(*) begin
        case (mr_select)
            3'd0: mr_data = mr0;
            3'd1: mr_data = mr1;
            3'd2: mr_data = mr2;
            3'd3: mr_data = mr3;
            3'd4: mr_data = mr4;
            3'd5: mr_data = mr5;
            3'd6: mr_data = mr6;
            default: mr_data = 17'h0;
        endcase
    end

endmodule

tb/ddr4_mode_reg_tb.v
`timescale 1ns/1ps
module ddr4_mode_reg_tb;

    reg        clk, rst_n;
    reg [4:0]  cfg_cl, cfg_cwl;
    reg [1:0]  cfg_al;
    reg [2:0]  cfg_rtt_nom, cfg_rtt_wr, cfg_rtt_park;
    reg [1:0]  cfg_drive_strength;
    reg [3:0]  cfg_wr_recovery;
    reg        cfg_dbi_rd_en, cfg_dbi_wr_en, cfg_ca_parity_en;
    reg [2:0]  mr_select;
    wire [16:0] mr_data;

    ddr4_mode_reg dut (
        .clk(clk), .rst_n(rst_n),
        .cfg_cl(cfg_cl), .cfg_cwl(cfg_cwl),
        .cfg_al(cfg_al),
        .cfg_rtt_nom(cfg_rtt_nom), .cfg_rtt_wr(cfg_rtt_wr),
        .cfg_rtt_park(cfg_rtt_park),
        .cfg_drive_strength(cfg_drive_strength),
        .cfg_wr_recovery(cfg_wr_recovery),
        .cfg_dbi_rd_en(cfg_dbi_rd_en), .cfg_dbi_wr_en(cfg_dbi_wr_en),
        .cfg_ca_parity_en(cfg_ca_parity_en),
        .mr_select(mr_select),
        .mr_data(mr_data)
    );

    initial clk = 0;
    always #5 clk = ~clk;

    initial begin
        $dumpfile("results/phase-core-ctrl/ddr4_mode_reg.vcd");
        $dumpvars(0, ddr4_mode_reg_tb);
    end

    task read_mr;
        input [2:0] sel;
        output [16:0] data;
        begin
            mr_select = sel;
            #1;
            data = mr_data;
        end
    endtask

    reg [16:0] data0, data1, data2, data3, data4, data5, data6;

    initial begin
        rst_n = 0;
        // cfg: CL=22, CWL=16, others typical
        cfg_cl             = 5'd22;
        cfg_cwl            = 5'd16;
        cfg_al             = 2'd0;
        cfg_rtt_nom        = 3'd4;
        cfg_rtt_wr         = 3'd1;
        cfg_rtt_park       = 3'd2;
        cfg_drive_strength = 2'd0;
        cfg_wr_recovery    = 4'd8;
        cfg_dbi_rd_en      = 1'b1;
        cfg_dbi_wr_en      = 1'b0;
        cfg_ca_parity_en   = 1'b1;
        mr_select          = 3'd0;

        repeat(5) @(posedge clk);
        rst_n = 1;
        @(posedge clk);

        // Read all MRs
        read_mr(3'd0, data0);
        read_mr(3'd1, data1);
        read_mr(3'd2, data2);
        read_mr(3'd3, data3);
        read_mr(3'd4, data4);
        read_mr(3'd5, data5);
        read_mr(3'd6, data6);

        $display("MR0=0x%05x MR1=0x%05x MR2=0x%05x MR3=0x%05x",
                 data0, data1, data2, data3);
        $display("MR4=0x%05x MR5=0x%05x MR6=0x%05x",
                 data4, data5, data6);

        // Verify MR2 bits[5:3] = (CWL-9)[2:0] = (16-9)[2:0] = 7[2:0] = 3'b111
        if (data2[5:3] !== 3'b111) begin
            $display("FAIL: MR2[5:3]=%0b, expected 3'b111 (CWL=16, cwl_enc=7)",
                     data2[5:3]);
            $fatal(1, "SIMULATION FAILED");
        end

        // Verify MR3, MR4, MR6 are zero
        if (data3 !== 17'h0)
            $fatal(1, "SIMULATION FAILED: MR3 should be 0, got 0x%05x", data3);
        if (data4 !== 17'h0)
            $fatal(1, "SIMULATION FAILED: MR4 should be 0, got 0x%05x", data4);
        if (data6 !== 17'h0)
            $fatal(1, "SIMULATION FAILED: MR6 should be 0, got 0x%05x", data6);

        // Verify MR5 DBI_RD bit (bit12)
        if (data5[12] !== 1'b1)
            $fatal(1, "SIMULATION FAILED: MR5[12] DBI_RD should be 1");
        // Verify MR5 CA_PARITY bit (bit0)
        if (data5[0] !== 1'b1)
            $fatal(1, "SIMULATION FAILED: MR5[0] CA_PARITY should be 1");

        // --- Test 2: Boundary CL minimum (CL=9, CWL=9) ---
        cfg_cl  = 5'd9;
        cfg_cwl = 5'd9;
        @(posedge clk);
        read_mr(3'd0, data0);
        read_mr(3'd2, data2);
        // CL=9 (01001): cfg_cl[2:0]=001, cfg_cl[3]=1
        // MR0[6:4] = cfg_cl[2:0] = 3'b001; MR0[12] = cfg_cl[3] = 1
        if (data0[6:4] !== 3'b001 || data0[12] !== 1'b1)
            $fatal(1, "SIMULATION FAILED: MR0 CL boundary min(9): got bits[6:4]=%b bit12=%b",
                   data0[6:4], data0[12]);
        // MR2[5:3] = CWL-9 = 0 → 3'b000
        if (data2[5:3] !== 3'b000)
            $fatal(1, "SIMULATION FAILED: MR2 CWL boundary min(9): got bits[5:3]=%b", data2[5:3]);
        $display("Boundary min CL=9/CWL=9 OK: MR0=0x%05x MR2=0x%05x", data0, data2);

        // --- Test 3: Boundary CL large (CL=24, CWL=18) ---
        cfg_cl  = 5'd24;
        cfg_cwl = 5'd18;
        @(posedge clk);
        read_mr(3'd0, data0);
        read_mr(3'd2, data2);
        // CL=24 (11000): cfg_cl[2:0]=000, cfg_cl[3]=1
        // MR0[6:4] = 3'b000; MR0[12] = 1
        if (data0[6:4] !== 3'b000 || data0[12] !== 1'b1)
            $fatal(1, "SIMULATION FAILED: MR0 CL boundary large(24): got bits[6:4]=%b bit12=%b",
                   data0[6:4], data0[12]);
        // CWL=18: cwl_enc = (18-9)[2:0] = 9[2:0] = 3'b001
        if (data2[5:3] !== 3'b001)
            $fatal(1, "SIMULATION FAILED: MR2 CWL boundary large(18): got bits[5:3]=%b", data2[5:3]);
        $display("Boundary large CL=24/CWL=18 OK: MR0=0x%05x MR2=0x%05x", data0, data2);

        $display("SIMULATION PASSED");
        $finish;
    end

endmodule

results/phase-core-ctrl/ddr4_mode_reg.vcd
$date
	Thu Mar 12 10:41:44 2026
$end
$version
	Icarus Verilog
$end
$timescale
	1ps
$end
$scope module ddr4_mode_reg_tb $end
$var wire 17 ! mr_data [16:0] $end
$var reg 2 " cfg_al [1:0] $end
$var reg 1 # cfg_ca_parity_en $end
$var reg 5 $ cfg_cl [4:0] $end
$var reg 5 % cfg_cwl [4:0] $end
$var reg 1 & cfg_dbi_rd_en $end
$var reg 1 ' cfg_dbi_wr_en $end
$var reg 2 ( cfg_drive_strength [1:0] $end
$var reg 3 ) cfg_rtt_nom [2:0] $end
$var reg 3 * cfg_rtt_park [2:0] $end
$var reg 3 + cfg_rtt_wr [2:0] $end
$var reg 4 , cfg_wr_recovery [3:0] $end
$var reg 1 - clk $end
$var reg 17 . data0 [16:0] $end
$var reg 17 / data1 [16:0] $end
$var reg 17 0 data2 [16:0] $end
$var reg 17 1 data3 [16:0] $end
$var reg 17 2 data4 [16:0] $end
$var reg 17 3 data5 [16:0] $end
$var reg 17 4 data6 [16:0] $end
$var reg 3 5 mr_select [2:0] $end
$var reg 1 6 rst_n $end
$scope module dut $end
$var wire 2 7 cfg_al [1:0] $end
$var wire 1 # cfg_ca_parity_en $end
$var wire 5 8 cfg_cl [4:0] $end
$var wire 5 9 cfg_cwl [4:0] $end
$var wire 1 & cfg_dbi_rd_en $end
$var wire 1 ' cfg_dbi_wr_en $end
$var wire 2 : cfg_drive_strength [1:0] $end
$var wire 3 ; cfg_rtt_nom [2:0] $end
$var wire 3 < cfg_rtt_park [2:0] $end
$var wire 3 = cfg_rtt_wr [2:0] $end
$var wire 4 > cfg_wr_recovery [3:0] $end
$var wire 1 - clk $end
$var wire 17 ? mr3 [16:0] $end
$var wire 17 @ mr4 [16:0] $end
$var wire 17 A mr6 [16:0] $end
$var wire 3 B mr_select [2:0] $end
$var wire 1 6 rst_n $end
$var wire 17 C mr5 [16:0] $end
$var wire 17 D mr2 [16:0] $end
$var wire 17 E mr1 [16:0] $end
$var wire 17 F mr0 [16:0] $end
$var wire 3 G cwl_enc [2:0] $end
$var reg 17 H mr_data [16:0] $end
$upscope $end
$scope task read_mr $end
$var reg 17 I data [16:0] $end
$var reg 3 J sel [2:0] $end
$upscope $end
$upscope $end
$enddefinitions $end
$comment Show the parameter values. $end
$dumpall
$end
#0
$dumpvars
bx J
bx I
b10000001100000 H
b111 G
b10000001100000 F
b10000000000 E
b1000111000 D
b1000010000001 C
b0 B
b0 A
b0 @
b0 ?
b1000 >
b1 =
b10 <
b100 ;
b0 :
b10000 9
b10110 8
b0 7
06
b0 5
bx 4
bx 3
bx 2
bx 1
bx 0
bx /
bx .
0-
b1000 ,
b1 +
b10 *
b100 )
b0 (
0'
1&
b10000 %
b10110 $
1#
b0 "
b10000001100000 !
$end
#5000
1-
#10000
0-
#15000
1-
#20000
0-
#25000
1-
#30000
0-
#35000
1-
#40000
0-
#45000
16
1-
#50000
0-
#55000
b0 J
1-
#56000
b10000000000 !
b10000000000 H
b1 5
b1 B
b1 J
b10000001100000 .
b10000001100000 I
#57000
b1000111000 !
b1000111000 H
b10 5
b10 B
b10 J
b10000000000 /
b10000000000 I
#58000
b0 !
b0 H
b11 5
b11 B
b11 J
b1000111000 0
b1000111000 I
#59000
b100 5
b100 B
b100 J
b0 1
b0 I
#60000
b1000010000001 !
b1000010000001 H
b101 5
b101 B
b101 J
b0 2
0-
#61000
b0 !
b0 H
b110 5
b110 B
b110 J
b1000010000001 3
b1000010000001 I
#62000
b0 4
b0 I
