rtl/ddr4_cmd_scheduler.v
// DDR4 Command Scheduler
// Single-bank open/closed-page FSM with command queue and refresh arbitration
module ddr4_cmd_scheduler (
    input  wire        clk,
    input  wire        rst_n,

    // Host command interface
    input  wire        cmd_valid,
    output reg         cmd_ready,
    input  wire [1:0]  cmd_type,   // 0=READ, 1=WRITE
    input  wire [31:0] cmd_addr,
    input  wire [3:0]  cmd_id,

    // Refresh interface
    input  wire        ref_req,
    input  wire [1:0]  ref_rank,
    input  wire [3:0]  ref_bank,
    output reg         ref_ack,

    // Timing gate
    input  wire [15:0] timing_ok,

    // DRAM command output
    output reg         dram_cmd_valid,
    output reg  [2:0]  dram_cmd_type,
    output reg  [1:0]  dram_rank,
    output reg  [1:0]  dram_bg,
    output reg  [1:0]  dram_ba,
    output reg  [16:0] dram_row,
    output reg  [9:0]  dram_col,

    // Data request signals
    output reg         rd_data_req,
    output reg  [3:0]  rd_data_id,
    output reg         wr_data_req,
    output reg  [3:0]  wr_data_id
);

    // Command type encoding
    localparam CMD_NOP  = 3'd0;
    localparam CMD_MRS  = 3'd1;
    localparam CMD_REF  = 3'd2;
    localparam CMD_PRE  = 3'd3;
    localparam CMD_ACT  = 3'd4;
    localparam CMD_WR   = 3'd5;
    localparam CMD_RD   = 3'd6;

    // Bank FSM states
    localparam [2:0]
        BS_IDLE        = 3'd0,
        BS_ACTIVATING  = 3'd1,
        BS_ACTIVE      = 3'd2,
        BS_READING     = 3'd3,
        BS_WRITING     = 3'd4,
        BS_PRECHARGING = 3'd5,
        BS_REFRESH     = 3'd6;

    // Address decode
    wire [1:0]  dec_rank = cmd_addr[27:26];
    wire [16:0] dec_row  = cmd_addr[25:9];
    wire [1:0]  dec_ba   = cmd_addr[8:7];
    wire [1:0]  dec_bg   = cmd_addr[6:5];
    wire [9:0]  dec_col  = {cmd_addr[4:3], cmd_addr[12:5]};

    // Timing check aliases
    wire t_rcd_ok  = timing_ok[0];
    wire t_rp_ok   = timing_ok[1];
    wire t_ras_ok  = timing_ok[2];
    wire t_faw_ok  = timing_ok[12];
    wire t_rrd_s_ok= timing_ok[7];
    wire t_rtp_ok  = timing_ok[11];
    wire t_wr_ok   = timing_ok[8];

    // Bank state machine (single bank per scheduler instance)
    reg  [2:0]  bank_state;
    reg  [16:0] open_row;
    reg  [1:0]  open_rank;
    reg  [1:0]  open_bg;
    reg  [1:0]  open_ba;

    // Stored command
    reg         pend_valid;
    reg  [1:0]  pend_type;
    reg  [31:0] pend_addr;
    reg  [3:0]  pend_id;

    // Decoded pending command address
    wire [1:0]  pend_rank = pend_addr[27:26];
    wire [16:0] pend_row  = pend_addr[25:9];
    wire [1:0]  pend_ba   = pend_addr[8:7];
    wire [1:0]  pend_bg   = pend_addr[6:5];
    wire [9:0]  pend_col  = {pend_addr[4:3], pend_addr[12:5]};

    always @(posedge clk) begin
        if (!rst_n) begin
            bank_state    <= BS_IDLE;
            open_row      <= 17'd0;
            open_rank     <= 2'd0;
            open_bg       <= 2'd0;
            open_ba       <= 2'd0;
            pend_valid    <= 1'b0;
            pend_type     <= 2'd0;
            pend_addr     <= 32'd0;
            pend_id       <= 4'd0;
            cmd_ready     <= 1'b1;
            dram_cmd_valid<= 1'b0;
            dram_cmd_type <= CMD_NOP;
            dram_rank     <= 2'd0;
            dram_bg       <= 2'd0;
            dram_ba       <= 2'd0;
            dram_row      <= 17'd0;
            dram_col      <= 10'd0;
            rd_data_req   <= 1'b0;
            rd_data_id    <= 4'd0;
            wr_data_req   <= 1'b0;
            wr_data_id    <= 4'd0;
            ref_ack       <= 1'b0;
        end else begin
            // Default pulse signals off
            dram_cmd_valid <= 1'b0;
            rd_data_req    <= 1'b0;
            wr_data_req    <= 1'b0;
            ref_ack        <= 1'b0;

            // Capture incoming command when ready
            if (cmd_valid && cmd_ready && !pend_valid) begin
                pend_valid <= 1'b1;
                pend_type  <= cmd_type;
                pend_addr  <= cmd_addr;
                pend_id    <= cmd_id;
                cmd_ready  <= 1'b0;
            end

            case (bank_state)
                BS_IDLE: begin
                    // Priority: refresh > pending command
                    if (ref_req && t_rp_ok) begin
                        bank_state     <= BS_REFRESH;
                        dram_cmd_valid <= 1'b1;
                        dram_cmd_type  <= CMD_REF;
                        dram_rank      <= ref_rank;
                        dram_bg        <= 2'd0;
                        dram_ba        <= 2'd0;
                        ref_ack        <= 1'b1;
                    end else if (pend_valid && t_rp_ok && t_rrd_s_ok && t_faw_ok) begin
                        bank_state     <= BS_ACTIVATING;
                        dram_cmd_valid <= 1'b1;
                        dram_cmd_type  <= CMD_ACT;
                        dram_rank      <= pend_rank;
                        dram_bg        <= pend_bg;
                        dram_ba        <= pend_ba;
                        dram_row       <= pend_row;
                        open_row       <= pend_row;
                        open_rank      <= pend_rank;
                        open_bg        <= pend_bg;
                        open_ba        <= pend_ba;
                    end
                end

                BS_ACTIVATING: begin
                    // Wait for tRCD
                    if (t_rcd_ok)
                        bank_state <= BS_ACTIVE;
                end

                BS_ACTIVE: begin
                    if (pend_valid && t_rcd_ok) begin
                        if (pend_type == 2'd1) begin
                            // WRITE
                            bank_state     <= BS_WRITING;
                            dram_cmd_valid <= 1'b1;
                            dram_cmd_type  <= CMD_WR;
                            dram_rank      <= pend_rank;
                            dram_bg        <= pend_bg;
                            dram_ba        <= pend_ba;
                            dram_col       <= pend_col;
                            wr_data_req    <= 1'b1;
                            wr_data_id     <= pend_id;
                            pend_valid     <= 1'b0;
                            cmd_ready      <= 1'b1;
                        end else begin
                            // READ
                            bank_state     <= BS_READING;
                            dram_cmd_valid <= 1'b1;
                            dram_cmd_type  <= CMD_RD;
                            dram_rank      <= pend_rank;
                            dram_bg        <= pend_bg;
                            dram_ba        <= pend_ba;
                            dram_col       <= pend_col;
                            rd_data_req    <= 1'b1;
                            rd_data_id     <= pend_id;
                            pend_valid     <= 1'b0;
                            cmd_ready      <= 1'b1;
                        end
                    end
                end

                BS_READING: begin
                    if (t_rtp_ok) begin
                        bank_state     <= BS_PRECHARGING;
                        dram_cmd_valid <= 1'b1;
                        dram_cmd_type  <= CMD_PRE;
                        dram_rank      <= open_rank;
                        dram_bg        <= open_bg;
                        dram_ba        <= open_ba;
                    end
                end

                BS_WRITING: begin
                    if (t_wr_ok && t_ras_ok) begin
                        bank_state     <= BS_PRECHARGING;
                        dram_cmd_valid <= 1'b1;
                        dram_cmd_type  <= CMD_PRE;
                        dram_rank      <= open_rank;
                        dram_bg        <= open_bg;
                        dram_ba        <= open_ba;
                    end
                end

                BS_PRECHARGING: begin
                    if (t_rp_ok)
                        bank_state <= BS_IDLE;
                end

                BS_REFRESH: begin
                    // tRFC handled by timing engine; return to IDLE when tRFC ok
                    if (timing_ok[13])
                        bank_state <= BS_IDLE;
                end

                default: bank_state <= BS_IDLE;
            endcase
        end
    end

endmodule

tb/ddr4_cmd_scheduler_tb.v
`timescale 1ns/1ps
module ddr4_cmd_scheduler_tb;

    reg        clk, rst_n;
    reg        cmd_valid;
    wire       cmd_ready;
    reg [1:0]  cmd_type;
    reg [31:0] cmd_addr;
    reg [3:0]  cmd_id;
    reg        ref_req;
    reg [1:0]  ref_rank;
    reg [3:0]  ref_bank;
    wire       ref_ack;
    reg [15:0] timing_ok;
    wire       dram_cmd_valid;
    wire [2:0] dram_cmd_type;
    wire [1:0] dram_rank, dram_bg, dram_ba;
    wire [16:0] dram_row;
    wire [9:0]  dram_col;
    wire        rd_data_req, wr_data_req;
    wire [3:0]  rd_data_id, wr_data_id;

    ddr4_cmd_scheduler dut (
        .clk(clk), .rst_n(rst_n),
        .cmd_valid(cmd_valid), .cmd_ready(cmd_ready),
        .cmd_type(cmd_type), .cmd_addr(cmd_addr), .cmd_id(cmd_id),
        .ref_req(ref_req), .ref_rank(ref_rank), .ref_bank(ref_bank),
        .ref_ack(ref_ack),
        .timing_ok(timing_ok),
        .dram_cmd_valid(dram_cmd_valid),
        .dram_cmd_type(dram_cmd_type),
        .dram_rank(dram_rank), .dram_bg(dram_bg), .dram_ba(dram_ba),
        .dram_row(dram_row), .dram_col(dram_col),
        .rd_data_req(rd_data_req), .rd_data_id(rd_data_id),
        .wr_data_req(wr_data_req), .wr_data_id(wr_data_id)
    );

    initial clk = 0;
    always #5 clk = ~clk;

    initial begin
        $dumpfile("results/phase-core-ctrl/ddr4_cmd_scheduler.vcd");
        $dumpvars(0, ddr4_cmd_scheduler_tb);
    end

    integer wait_cnt;

    // Drive stimulus on negedge to avoid posedge race with RTL
    task issue_cmd;
        input [1:0]  ctype;
        input [31:0] addr;
        input [3:0]  id;
        begin
            @(negedge clk);
            cmd_valid = 1'b1;
            cmd_type  = ctype;
            cmd_addr  = addr;
            cmd_id    = id;
            // Hold until command is accepted (cmd_ready goes low)
            @(posedge clk); // RTL samples cmd_valid=1, cmd_ready=1 → latches
            @(negedge clk);
            cmd_valid = 1'b0;
        end
    endtask

    // Wait for a specific dram_cmd_type; check on posedge
    task wait_for_dram_cmd;
        input [2:0] expected;
        input integer timeout;
        begin
            wait_cnt = 0;
            @(posedge clk);
            while (!(dram_cmd_valid && dram_cmd_type == expected)) begin
                wait_cnt = wait_cnt + 1;
                if (wait_cnt >= timeout)
                    $fatal(1, "SIMULATION FAILED: timeout waiting for dram_cmd_type=%0d", expected);
                @(posedge clk);
            end
        end
    endtask

    initial begin
        rst_n       = 0;
        cmd_valid   = 0;
        cmd_type    = 0;
        cmd_addr    = 0;
        cmd_id      = 0;
        ref_req     = 0;
        ref_rank    = 0;
        ref_bank    = 0;
        timing_ok   = 16'hFFFF;  // all timing satisfied

        repeat(5) @(posedge clk);
        @(negedge clk);
        rst_n = 1;
        repeat(2) @(posedge clk);

        // --- Test 1: WRITE command → ACT → WR → PRE ---
        $display("Test 1: WRITE sequence ACT->WR->PRE");
        issue_cmd(2'd1, 32'h04000000, 4'h1); // WRITE

        wait_for_dram_cmd(3'd4, 50); // CMD_ACT=4
        $display("  Saw ACT");

        wait_for_dram_cmd(3'd5, 50); // CMD_WR=5
        $display("  Saw WR");
        if (!wr_data_req)
            $fatal(1, "SIMULATION FAILED: wr_data_req not asserted with WR");

        wait_for_dram_cmd(3'd3, 50); // CMD_PRE=3
        $display("  Saw PRE");

        repeat(5) @(posedge clk);

        // --- Test 2: READ command → ACT → RD → PRE ---
        $display("Test 2: READ sequence ACT->RD->PRE");
        issue_cmd(2'd0, 32'h04000000, 4'h2); // READ

        wait_for_dram_cmd(3'd4, 50); // ACT
        $display("  Saw ACT");
        wait_for_dram_cmd(3'd6, 50); // CMD_RD=6
        $display("  Saw RD");
        if (!rd_data_req)
            $fatal(1, "SIMULATION FAILED: rd_data_req not asserted with RD");
        wait_for_dram_cmd(3'd3, 50); // PRE
        $display("  Saw PRE");

        repeat(5) @(posedge clk);

        // --- Test 3: Refresh preemption in idle state ---
        $display("Test 3: Refresh preemption");
        @(negedge clk);
        ref_req  = 1'b1;
        ref_rank = 2'd0;
        ref_bank = 4'd0;

        wait_cnt = 0;
        @(posedge clk);
        while (!ref_ack) begin
            wait_cnt = wait_cnt + 1;
            if (wait_cnt >= 50)
                $fatal(1, "SIMULATION FAILED: ref_ack not seen within timeout");
            @(posedge clk);
        end
        $display("  ref_ack received");
        @(negedge clk);
        ref_req = 1'b0;
        $display("  Refresh preemption handled");

        repeat(5) @(posedge clk);

        // --- Test 4: Multi-rank — issue READ to rank 0 and rank 1 ---
        $display("Test 4: Multi-rank commands (rank 0 and rank 1)");
        // Rank is decoded from cmd_addr[27:26]
        // Rank 0: addr = 32'h04000000 (bits[27:26]=01 → rank=1) — use explicit ranks
        // Rank 0 address: bits[27:26] = 2'b00 → addr = 32'h00000000
        // Rank 1 address: bits[27:26] = 2'b01 → addr = 32'h04000000
        issue_cmd(2'd0, 32'h00000100, 4'h3); // READ rank=0

        wait_for_dram_cmd(3'd4, 50); // ACT
        if (dram_rank !== 2'd0)
            $fatal(1, "SIMULATION FAILED: expected rank=0 for rank-0 cmd, got %0d", dram_rank);
        $display("  Rank 0 ACT issued (rank=%0d)", dram_rank);
        wait_for_dram_cmd(3'd6, 50); // RD
        wait_for_dram_cmd(3'd3, 50); // PRE

        repeat(5) @(posedge clk);

        issue_cmd(2'd0, 32'h04000200, 4'h4); // READ rank=1

        wait_for_dram_cmd(3'd4, 50); // ACT
        if (dram_rank !== 2'd1)
            $fatal(1, "SIMULATION FAILED: expected rank=1 for rank-1 cmd, got %0d", dram_rank);
        $display("  Rank 1 ACT issued (rank=%0d)", dram_rank);
        wait_for_dram_cmd(3'd6, 50); // RD
        wait_for_dram_cmd(3'd3, 50); // PRE

        $display("  Multi-rank commands OK");

        repeat(5) @(posedge clk);
        $display("SIMULATION PASSED");
        $finish;
    end

endmodule

results/phase-core-ctrl/ddr4_cmd_scheduler.vcd
$date
	Thu Mar 12 10:41:44 2026
$end
$version
	Icarus Verilog
$end
$timescale
	1ps
$end
$scope module ddr4_cmd_scheduler_tb $end
$var wire 1 ! wr_data_req $end
$var wire 4 " wr_data_id [3:0] $end
$var wire 1 # ref_ack $end
$var wire 1 $ rd_data_req $end
$var wire 4 % rd_data_id [3:0] $end
$var wire 17 & dram_row [16:0] $end
$var wire 2 ' dram_rank [1:0] $end
$var wire 10 ( dram_col [9:0] $end
$var wire 1 ) dram_cmd_valid $end
$var wire 3 * dram_cmd_type [2:0] $end
$var wire 2 + dram_bg [1:0] $end
$var wire 2 , dram_ba [1:0] $end
$var wire 1 - cmd_ready $end
$var reg 1 . clk $end
$var reg 32 / cmd_addr [31:0] $end
$var reg 4 0 cmd_id [3:0] $end
$var reg 2 1 cmd_type [1:0] $end
$var reg 1 2 cmd_valid $end
$var reg 4 3 ref_bank [3:0] $end
$var reg 2 4 ref_rank [1:0] $end
$var reg 1 5 ref_req $end
$var reg 1 6 rst_n $end
$var reg 16 7 timing_ok [15:0] $end
$var integer 32 8 wait_cnt [31:0] $end
$scope module dut $end
$var wire 1 . clk $end
$var wire 32 9 cmd_addr [31:0] $end
$var wire 4 : cmd_id [3:0] $end
$var wire 2 ; cmd_type [1:0] $end
$var wire 1 2 cmd_valid $end
$var wire 4 < ref_bank [3:0] $end
$var wire 2 = ref_rank [1:0] $end
$var wire 1 5 ref_req $end
$var wire 1 6 rst_n $end
$var wire 16 > timing_ok [15:0] $end
$var wire 1 ? t_wr_ok $end
$var wire 1 @ t_rtp_ok $end
$var wire 1 A t_rrd_s_ok $end
$var wire 1 B t_rp_ok $end
$var wire 1 C t_rcd_ok $end
$var wire 1 D t_ras_ok $end
$var wire 1 E t_faw_ok $end
$var wire 17 F pend_row [16:0] $end
$var wire 2 G pend_rank [1:0] $end
$var wire 10 H pend_col [9:0] $end
$var wire 2 I pend_bg [1:0] $end
$var wire 2 J pend_ba [1:0] $end
$var wire 17 K dec_row [16:0] $end
$var wire 2 L dec_rank [1:0] $end
$var wire 10 M dec_col [9:0] $end
$var wire 2 N dec_bg [1:0] $end
$var wire 2 O dec_ba [1:0] $end
$var parameter 3 P BS_ACTIVATING $end
$var parameter 3 Q BS_ACTIVE $end
$var parameter 3 R BS_IDLE $end
$var parameter 3 S BS_PRECHARGING $end
$var parameter 3 T BS_READING $end
$var parameter 3 U BS_REFRESH $end
$var parameter 3 V BS_WRITING $end
$var parameter 3 W CMD_ACT $end
$var parameter 3 X CMD_MRS $end
$var parameter 3 Y CMD_NOP $end
$var parameter 3 Z CMD_PRE $end
$var parameter 3 [ CMD_RD $end
$var parameter 3 \ CMD_REF $end
$var parameter 3 ] CMD_WR $end
$var reg 3 ^ bank_state [2:0] $end
$var reg 1 - cmd_ready $end
$var reg 2 _ dram_ba [1:0] $end
$var reg 2 ` dram_bg [1:0] $end
$var reg 3 a dram_cmd_type [2:0] $end
$var reg 1 ) dram_cmd_valid $end
$var reg 10 b dram_col [9:0] $end
$var reg 2 c dram_rank [1:0] $end
$var reg 17 d dram_row [16:0] $end
$var reg 2 e open_ba [1:0] $end
$var reg 2 f open_bg [1:0] $end
$var reg 2 g open_rank [1:0] $end
$var reg 17 h open_row [16:0] $end
$var reg 32 i pend_addr [31:0] $end
$var reg 4 j pend_id [3:0] $end
$var reg 2 k pend_type [1:0] $end
$var reg 1 l pend_valid $end
$var reg 4 m rd_data_id [3:0] $end
$var reg 1 $ rd_data_req $end
$var reg 1 # ref_ack $end
$var reg 4 n wr_data_id [3:0] $end
$var reg 1 ! wr_data_req $end
$upscope $end
$scope task issue_cmd $end
$var reg 32 o addr [31:0] $end
$var reg 2 p ctype [1:0] $end
$var reg 4 q id [3:0] $end
$upscope $end
$scope task wait_for_dram_cmd $end
$var reg 3 r expected [2:0] $end
$var integer 32 s timeout [31:0] $end
$upscope $end
$upscope $end
$enddefinitions $end
$comment Show the parameter values. $end
$dumpall
b101 ]
b10 \
b110 [
b11 Z
b0 Y
b1 X
b100 W
b100 V
b110 U
b11 T
b101 S
b0 R
b10 Q
b1 P
$end
#0
$dumpvars
bx s
bx r
bx q
bx p
bx o
bx n
bx m
xl
bx k
bx j
bx i
bx h
bx g
bx f
bx e
bx d
bx c
bx b
bx a
bx `
bx _
bx ^
b0 O
b0 N
b0 M
b0 L
b0 K
bx J
bx I
bx H
bx G
bx F
1E
1D
1C
1B
1A
1@
1?
b1111111111111111 >
b0 =
b0 <
b0 ;
b0 :
b0 9
bx 8
b1111111111111111 7
06
05
b0 4
b0 3
02
b0 1
b0 0
b0 /
0.
x-
bx ,
bx +
bx *
x)
bx (
bx '
bx &
bx %
x$
x#
bx "
x!
$end
#5000
b0 G
b0 F
b0 J
b0 I
b0 H
0#
b0 "
b0 n
0!
b0 %
b0 m
0$
b0 (
b0 b
b0 &
b0 d
b0 ,
b0 _
b0 +
b0 `
b0 '
b0 c
b0 *
b0 a
0)
1-
b0 j
b0 i
b0 k
0l
b0 e
b0 f
b0 g
b0 h
b0 ^
1.
#10000
0.
#15000
1.
#20000
0.
#25000
1.
#30000
0.
#35000
1.
#40000
0.
#45000
1.
#50000
16
0.
#55000
1.
#60000
0.
#65000
b1 q
b100000000000000000000000000 o
b1 p
1.
#70000
b1 L
b1 0
b1 :
b100000000000000000000000000 /
b100000000000000000000000000 9
b1 1
b1 ;
12
0.
#75000
b1 G
0-
b1 j
b100000000000000000000000000 i
b1 k
1l
1.
#80000
b0 8
b110010 s
b100 r
02
0.
#85000
b1 g
b1 '
b1 c
b100 *
b100 a
1)
b1 ^
b1 8
1.
#90000
0.
#95000
b10 ^
0)
b0 8
b101 r
1.
#100000
0.
#105000
1-
0l
b1 "
b1 n
1!
b101 *
b101 a
1)
b100 ^
b1 8
1.
#110000
0.
#115000
b11 *
b11 a
b101 ^
0!
1)
b0 8
b11 r
1.
#120000
0.
#125000
b0 ^
0)
1.
#130000
0.
#135000
1.
#140000
0.
#145000
1.
#150000
0.
#155000
1.
#160000
0.
#165000
1.
#170000
0.
#175000
b10 q
b0 p
1.
#180000
b10 0
b10 :
b0 1
b0 ;
12
0.
#185000
0-
b10 j
b0 k
1l
1.
#190000
b100 r
02
0.
#195000
b100 *
b100 a
1)
b1 ^
b1 8
1.
#200000
0.
#205000
b10 ^
0)
b0 8
b110 r
1.
#210000
0.
#215000
1-
0l
b10 %
b10 m
1$
b110 *
b110 a
1)
b11 ^
b1 8
1.
#220000
0.
#225000
b11 *
b11 a
b101 ^
0$
1)
b0 8
b11 r
1.
#230000
0.
#235000
b0 ^
0)
1.
#240000
0.
#245000
1.
#250000
0.
#255000
1.
#260000
0.
#265000
1.
#270000
0.
#275000
1.
#280000
0.
#285000
1.
#290000
15
0.
#295000
1#
b0 '
b0 c
b10 *
b10 a
1)
b110 ^
b1 8
1.
#300000
0.
#305000
b0 ^
0#
0)
1.
#310000
05
0.
